Workbook

Sheet Main
B1: IR
B3: HQ: Denver, CO
B4: CEO | C4: Tom Palmer | J4: P | K4: 115.47 | N4: News | O4: Contains
B5: New CEO | C5: Natascha Viljoen's | J5: S | K5: 1053.6923 | L5: Q226 | N5: 45632 | O5: selling Cripple Creek & Victor operation in Colorado to SSR Mining for up to $275m
B6: CFO | J6: MC | K6: =+K4*K5 -> 121669.85 | N6: 45621 | O6: selling Eleonore operation in Northern Quebec
J7: C | K7: 9009 | L7: =+L5 -> Q226 | N7: 45614 | O7: selling Musselwhite operation in Ontario, Canada
B8: P * Q | J8: D | K8: 5083 | L8: =+L7 -> Q226 | N8: 45594 | O8: 1st battery ev large mining truck deployed in cripple creek colorado
B9: P: LBMA (Gold),LME (Cu), Timing | J9: EV | K9: =+K6-K7+K8 -> 117743.85 | N9: 45573 | O9: selling Akyem operation in Repub of Ghana to Zijin Mining Group
B10: Q: Production capability (mine capacity, mill throughput, weather), recovery (metallurgy/cil/heap effic, Ownership) | N10: 45568 | O10: announces Tom palmer as Internal council on Mining and Metald) ICMM chair
N11: 45588 | O11: Q4 guidance: 1.8m oz of gold
B12: Equity Method Investments | N12: 45497 | O12: annual prod guide: 6.9m oz
B13: Pueblo Viejo Mine (50%) | N13: 45407 | O13: reaffirmed guide
B14: NuevaUnion Project (50%)
B15: Lundin Gold (32%)
B16: Norte Abierto Project (50%) | N16: Press Releases
B17: Greatland (10%) | N17: 45953 | O17: Q325 results
N18: 45770 | O18: Q125 Results
N19: 45684 | O19: early redemption of 5.3% notes due 2026
N20: 45684 | O20: sale of porcupine operation for up $425m
N21: Q226 results

Sheet Model
A1: Main
C2: Actuals | D2: Actuals | E2: Actuals | F2: Actuals | G2: Actuals | H2: Actuals | I2: Actuals | J2: Actuals | K2: Actuals | L2: Actuals | M2: Estimate | N2: Estimate | Q2: Actuals | R2: Actuals | S2: Actuals | T2: Estimate | U2: Estimate | V2: Estimate | W2: Estimate | X2: Estimate | Y2: Estimate | Z2: Estimate | AA2: Estimate | AB2: Estimate | AC2: Estimate
C3: Q124 | D3: Q224 | E3: Q324 | F3: Q424 | G3: Q125 | H3: Q225 | I3: Q325 | J3: Q425 | K3: Q126 | L3: Q226 | M3: Q326 | N3: Q426 | Q3: 2023 | R3: =+Q3+1 -> 2024 | S3: =+R3+1 -> 2025 | T3: 2026 | U3: =+T3+1 -> 2027 | V3: =+U3+1 -> 2028 | W3: =+V3+1 -> 2029 | X3: =+W3+1 -> 2030 | Y3: =+X3+1 -> 2031 | Z3: =+Y3+1 -> 2032 | AA3: =+Z3+1 -> 2033 | AB3: =+AA3+1 -> 2034 | AC3: =+AB3+1 -> 2035 | AD3: 1 | AE3: =+AD3+1 -> 2 | AF3: =+AE3+1 -> 3 | AG3: =+AF3+1 -> 4 | AH3: =+AG3+1 -> 5 | AI3: =+AH3+1 -> 6 | AJ3: =+AI3+1 -> 7 | AK3: =+AJ3+1 -> 8 | AL3: =+AK3+1 -> 9 | ... AR3: =+AQ3+1 -> 15
B4: Gold Oz Sold (koz) | C4: 1581 | D4: 1528 | E4: 1551 | F4: 1811 | G4: 1442 | H4: 1380 | I4: 1319 | J4: 1378 | K4: 1232 | L4: 1195 | M4: =+I4*0.9 -> 1187.1 | N4: =+J4*0.9 -> 1240.2 | Q4: 5340 | R4: =SUM(C4:F4) -> 6471 | S4: =SUM(G4:J4) -> 5519 | T4: =SUM(K4:N4) -> 4854.3 | U4: =+T4-1.1 -> 4853.2 | V4: =+U4-1.1 -> 4852.1 | W4: =+V4-1.1 -> 4851 | X4: =+W4-1.1 -> 4849.9 | Y4: =+X4-1.1 -> 4848.8 | Z4: =+Y4-1.1 -> 4847.7 | AA4: =+Z4-1.1 -> 4846.6 | AB4: =+AA4-1.1 -> 4845.5 | AC4: =+AB4-1.1 -> 4844.4
B5: Realized Gold Price ($/oz) | C5: 2090 | D5: 2347 | E5: 2518 | F5: 2643 | G5: 2944 | H5: 3320 | I5: 3539 | J5: 4216 | K5: 4900 | L5: 4414 | M5: 4300 | N5: 4500 | Q5: 1954 | R5: =+R6/R4 * 10^3 -> 2408.0354 | S5: =+S6/S4 * 10^3 -> 3497.8143 | T5: =+T6/T4 * 10^3 -> 4345.8354 | U5: =+T5*1.02 -> 4432.7522 | V5: =+U5*1.02 -> 4521.4072 | W5: =+V5*1.02 -> 4611.8353 | X5: =+W5*1.02 -> 4704.072 | Y5: =+X5*1.02 -> 4798.1535 | Z5: =+Y5*1.02 -> 4894.1166 | AA5: =+Z5*1.02 -> 4991.9989 | AB5: =+AA5*1.02 -> 5091.8389 | AC5: =+AB5*1.02 -> 5193.6756
B6: Gold Revenue | C6: =+(C4*C5) / 10^3 -> 3304.29 | D6: =+(D4*D5) / 10^3 -> 3586.216 | E6: =+(E4*E5) / 10^3 -> 3905.418 | F6: =+(F4*F5) / 10^3 -> 4786.473 | G6: =+(G4*G5) / 10^3 -> 4245.248 | H6: =+(H4*H5) / 10^3 -> 4581.6 | I6: =+(I4*I5) / 10^3 -> 4667.941 | J6: =+(J4*J5) / 10^3 -> 5809.648 | ... N6: =+(N4*N5) / 10^3 -> 5580.9 | Q6: =+(Q4*Q5) / 10^3 -> 10434.36 | R6: =SUM(C6:F6) -> 15582.397 | S6: =SUM(G6:J6) -> 19304.437 | T6: =SUM(H6:K6) -> 21095.989 | U6: =+(U4*U5) / 10^3 -> 21513.033 | V6: =+(V4*V5) / 10^3 -> 21938.32 | W6: =+(W4*W5) / 10^3 -> 22372.013 | X6: =+(X4*X5) / 10^3 -> 22814.279 | Y6: =+(Y4*Y5) / 10^3 -> 23265.287 | Z6: =+(Z4*Z5) / 10^3 -> 23725.209 | AA6: =+(AA4*AA5) / 10^3 -> 24194.222 | AB6: =+(AB4*AB5) / 10^3 -> 24672.505 | AC6: =+(AC4*AC5) / 10^3 -> 25160.242
B7: Other Metals | C7: =4023-C6 -> 718.71 | D7: =4402-D6 -> 815.784 | E7: =4605-E6 -> 699.582 | F7: =5652-F6 -> 865.527 | G7: =5011-G6 -> 765.752 | H7: =5317-H6 -> 735.4 | I7: =5524-I6 -> 856.059 | J7: =6818-J6 -> 1008.352 | K7: =7307-K6 -> 1270.2 | L7: =6118-L6 -> 843.27 | M7: =AVERAGE(K7:L7) -> 1056.735 | N7: =AVERAGE(L7:M7) -> 950.0025 | Q7: =11812-Q6 -> 1377.64 | R7: =SUM(C7:F7) -> 3099.603 | S7: =SUM(G7:J7) -> 3365.563 | T7: =SUM(K7:N7) -> 4120.2075 | U7: =+T7*1.01 -> 4161.4096 | V7: =+U7*1.01 -> 4203.0237 | W7: =+V7*1.01 -> 4245.0539 | X7: =+W7*1.01 -> 4287.5044 | Y7: =+X7*1.01 -> 4330.3795 | Z7: =+Y7*1.01 -> 4373.6833 | AA7: =+Z7*1.01 -> 4417.4201 | AB7: =+AA7*1.01 -> 4461.5943 | AC7: =+AB7*1.01 -> 4506.2103
B8: Total Revenue | C8: =SUM(C6:C7) -> 4023 | D8: =SUM(D6:D7) -> 4402 | E8: =SUM(E6:E7) -> 4605 | F8: =SUM(F6:F7) -> 5652 | G8: =SUM(G6:G7) -> 5011 | H8: =SUM(H6:H7) -> 5317 | I8: =SUM(I6:I7) -> 5524 | J8: =SUM(J6:J7) -> 6818 | ... N8: =SUM(N6:N7) -> 6530.9025 | Q8: =SUM(Q6:Q7) -> 11812 | R8: =SUM(C8:F8) -> 18682 | S8: =SUM(G8:J8) -> 22670 | T8: =SUM(H8:K8) -> 24966 | U8: =+SUM(U6:U7) -> 25674.442 | V8: =+SUM(V6:V7) -> 26141.344 | W8: =+SUM(W6:W7) -> 26617.067 | X8: =+SUM(X6:X7) -> 27101.783 | Y8: =+SUM(Y6:Y7) -> 27595.666 | Z8: =+SUM(Z6:Z7) -> 28098.892 | AA8: =+SUM(AA6:AA7) -> 28611.642 | AB8: =+SUM(AB6:AB7) -> 29134.1 | AC8: =+SUM(AC6:AC7) -> 29666.453
B9: Costs Applicable to Sales | C9: =1690+416 -> 2106 | D9: =1777+379 -> 2156 | E9: 2310 | F9: 2391 | G9: 2106 | H9: 2001 | I9: 1951 | J9: 2027 | K9: 1937 | L9: 2088 | M9: =+M8*(L9/L8) -> 2102.7658 | N9: =+N8*(M9/M8) -> 2228.9187 | Q9: =5689+1010 -> 6699 | R9: =SUM(C9:F9) -> 8963 | S9: =SUM(G9:J9) -> 8085 | T9: =SUM(K9:N9) -> 8356.6845 | U9: =+U8*(T9/T8) -> 8593.8162 | V9: =+V8*(U9/U8) -> 8750.0985 | W9: =+W8*(V9/V8) -> 8909.334 | X9: =+X8*(W9/W8) -> 9071.5795 | Y9: =+Y8*(X9/X8) -> 9236.8932 | Z9: =+Z8*(Y9/Y8) -> 9405.3343 | AA9: =+AA8*(Z9/Z8) -> 9576.9633 | AB9: =+AB8*(AA9/AA8) -> 9751.8416 | AC9: =+AC8*(AB9/AB8) -> 9930.0322
B10: Mine Level Cash Margin | C10: =+C8-C9 -> 1917 | D10: =+D8-D9 -> 2246 | E10: =+E8-E9 -> 2295 | F10: =+F8-F9 -> 3261 | G10: =+G8-G9 -> 2905 | H10: =+H8-H9 -> 3316 | I10: =+I8-I9 -> 3573 | J10: =+J8-J9 -> 4791 | ... N10: =+N8-N9 -> 4301.9838 | Q10: =+Q8-Q9 -> 5113 | R10: =SUM(C10:F10) -> 9719 | S10: =SUM(G10:J10) -> 14585 | T10: =SUM(H10:K10) -> 17050 | U10: =+U8-U9 -> 17080.626 | V10: =+V8-V9 -> 17391.245 | W10: =+W8-W9 -> 17707.733 | X10: =+X8-X9 -> 18030.204 | Y10: =+Y8-Y9 -> 18358.773 | Z10: =+Z8-Z9 -> 18693.558 | AA10: =+AA8-AA9 -> 19034.679 | AB10: =+AB8-AB9 -> 19382.258 | AC10: =+AC8-AC9 -> 19736.42
B11: CapEx | C11: 850 | D11: 800 | E11: 877 | F11: 875 | G11: 826 | H11: 674 | I11: 727 | J11: 808 | K11: 641 | L11: 719 | M11: =+M$10*(L11/L$10) -> 724.08459 | N11: =+N$10*(M11/M$10) -> 767.52515 | Q11: 2666 | R11: =SUM(C11:F11) -> 3402 | S11: =SUM(G11:J11) -> 3035 | T11: =SUM(K11:N11) -> 2851.6097 | U11: =+U$10*(T11/T$10) -> 2856.732 | V11: =+V$10*(U11/U$10) -> 2908.6829 | W11: =+W$10*(V11/V$10) -> 2961.6155 | X11: =+X$10*(W11/W$10) -> 3015.5487 | Y11: =+Y$10*(X11/X$10) -> 3070.5018 | Z11: =+Z$10*(Y11/Y$10) -> 3126.4945 | AA11: =+AA$10*(Z11/Z$10) -> 3183.5469 | AB11: =+AB$10*(AA11/AA$10) -> 3241.6795 | AC11: =+AC$10*(AB11/AB$10) -> 3300.9131
B12: G&A | C12: 101 | D12: 100 | E12: 113 | F12: 128 | G12: 110 | H12: 95 | I12: 86 | J12: 91 | K12: 79 | L12: 74 | M12: =+M$10*(L12/L$10) -> 74.52331 | N12: =+N$10*(M12/M$10) -> 78.994244 | Q12: 299 | R12: =SUM(C12:F12) -> 442 | S12: =SUM(G12:J12) -> 382 | T12: =SUM(K12:N12) -> 306.51755 | U12: =+U$10*(T12/T$10) -> 307.06814 | V12: =+V$10*(U12/U$10) -> 312.65231 | W12: =+W$10*(V12/V$10) -> 318.342 | X12: =+X$10*(W12/W$10) -> 324.13924 | Y12: =+Y$10*(X12/X$10) -> 330.04611 | Z12: =+Z$10*(Y12/Y$10) -> 336.06473 | AA12: =+AA$10*(Z12/Z$10) -> 342.19725 | AB12: =+AB$10*(AA12/AA$10) -> 348.44588 | AC12: =+AC$10*(AB12/AB$10) -> 354.81286
B13: Interest | C13: 93 | D13: 103 | E13: 86 | F13: 93 | G13: 79 | H13: 65 | I13: 52 | J13: 33 | K13: 39 | L13: 35 | M13: =+M$10*(L13/L$10) -> 35.247511 | N13: =+N$10*(M13/M$10) -> 37.362142 | Q13: 243 | R13: =SUM(C13:F13) -> 375 | S13: =SUM(G13:J13) -> 229 | T13: =SUM(K13:N13) -> 146.60965 | U13: =+U$10*(T13/T$10) -> 146.873 | V13: =+V$10*(U13/U$10) -> 149.54395 | W13: =+W$10*(V13/V$10) -> 152.26537 | X13: =+X$10*(W13/W$10) -> 155.03824 | Y13: =+Y$10*(X13/X$10) -> 157.86354 | Z13: =+Z$10*(Y13/Y$10) -> 160.74229 | AA13: =+AA$10*(Z13/Z$10) -> 163.67552 | AB13: =+AB$10*(AA13/AA$10) -> 166.66429 | AC13: =+AC$10*(AB13/AB$10) -> 169.70966
B14: Taxes | C14: 260 | D14: 191 | E14: 244 | F14: 702 | G14: 647 | H14: 1092 | I14: 787 | J14: 2070 | K14: 1404 | L14: 952 | M14: =+M$10*(L14/L$10) -> 958.73231 | N14: =+N$10*(M14/M$10) -> 1016.2503 | Q14: 526 | R14: =SUM(C14:F14) -> 1397 | S14: =SUM(G14:J14) -> 4596 | T14: =SUM(K14:N14) -> 4330.9826 | U14: =+U$10*(T14/T$10) -> 4338.7621 | V14: =+V$10*(U14/U$10) -> 4417.6645 | W14: =+W$10*(V14/V$10) -> 4498.0577 | X14: =+X$10*(W14/W$10) -> 4579.9706 | Y14: =+Y$10*(X14/X$10) -> 4663.4326 | Z14: =+Z$10*(Y14/Y$10) -> 4748.4735 | AA14: =+AA$10*(Z14/Z$10) -> 4835.1239 | AB14: =+AB$10*(AA14/AA$10) -> 4923.4148 | AC14: =+AC$10*(AB14/AB$10) -> 5013.3779
B15: Free Cash Flow | C15: =+C10-SUM(C11:C14) -> 613 | D15: =+D10-SUM(D11:D14) -> 1052 | E15: =+E10-SUM(E11:E14) -> 975 | F15: =+F10-SUM(F11:F14) -> 1463 | G15: =+G10-SUM(G11:G14) -> 1243 | H15: =+H10-SUM(H11:H14) -> 1390 | I15: =+I10-SUM(I11:I14) -> 1921 | J15: =+J10-SUM(J11:J14) -> 1789 | ... N15: =+N10-SUM(N11:N14) -> 2401.852 | Q15: =SUM(B15:E15) -> 2640 | R15: =SUM(C15:F15) -> 4103 | S15: =SUM(G15:J15) -> 6343 | T15: =SUM(H15:K15) -> 8307 | U15: =SUM(I15:L15) -> 9167 | V15: =SUM(J15:M15) -> 9511.9114 | W15: =SUM(K15:N15) -> 10124.763 | X15: =SUM(L15:O15) -> 6917.7635 | Y15: =SUM(M15:P15) -> 4667.7635 | Z15: =SUM(N15:Q15) -> 5041.852 | ... AC15: =SUM(Q15:T15) -> 21393 | AD15: =+AC15*(1+$AF$17) -> 20323.35 | AE15: =+AD15*(1+$AF$17) -> 19307.182 | AF15: =+AE15*(1+$AF$17) -> 18341.823 | AG15: =+AF15*(1+$AF$17) -> 17424.732 | AH15: =+AG15*(1+$AF$17) -> 16553.496 | AI15: =+AH15*(1+$AF$17) -> 15725.821 | AJ15: =+AI15*(1+$AF$17) -> 14939.53 | AK15: =+AJ15*(1+$AF$17) -> 14192.553 | ... AR15: =+AQ15*(1+$AF$17) -> 9911.1893
B16: Reported Free Cash Flow | C16: -74 | D16: 594 | E16: 760 | F16: 1636 | G16: 1205 | H16: 1710 | I16: 1571 | J16: 2813 | K16: 3144 | L16: 2205 | Q16: 88 | R16: =SUM(C16:F16) -> 2916 | S16: =SUM(G16:J16) -> 7299
B17: Difference | R17: =+R15/R16-1 -> 0.40706447 | S17: =+S15/S16-1 -> -0.13097685 | AE17: Terminal (15yrs) | AF17: -0.05
AE18: Discount | AF18: 0.08 | AG18: 0.085 | AH18: 0.09 | AI18: 0.095 | AJ18: 0.1
AE19: NPV | AF19: =NPV(AF18,$T$15:$AR$15) -> 123070.48 | AG19: =NPV(AG18,$T$15:$AR$15) -> 117267.95 | AH19: =NPV(AH18,$T$15:$AR$15) -> 111858.27 | AI19: =NPV(AI18,$T$15:$AR$15) -> 106809.81 | AJ19: =NPV(AJ18,$T$15:$AR$15) -> 102093.83
AE20: Shares | AF20: =+Main!K5 -> 1053.6923
AE21: Estimate | AF21: =+AF19/AF20 -> 116.79927 | AG21: =+AG19/$AF$20 -> 111.29241 | AH21: =+AH19/$AF$20 -> 106.15838 | AI21: =+AI19/$AF$20 -> 101.36718 | AJ21: =+AJ19/$AF$20 -> 96.891504
AE22: Upside | AF22: =+AF21/AF27-1 -> 0.011511779 | AG22: =+AG21/$AF$27-1 -> -0.036179007 | AH22: =+AH21/$AF$27-1 -> -0.080640994 | AI22: =+AI21/$AF$27-1 -> -0.12213406 | AJ22: =+AJ21/$AF$27-1 -> -0.16089457
AE23: P(x) | AF23: 1 | AG23: 0 | AH23: 0 | AI23: 0 | AJ23: 0 | AK23: =SUM(AF23:AJ23) -> 1
AE26: Estimate | AF26: =(AF21*AF23)+(AG21*AG23)+(AH21*AH23)+(AI21*AI23)+(AJ21*AJ23) -> 116.79927
AE27: Current | AF27: =+Main!K4 -> 115.47
AE28: Upside | AF28: =+AF26/AF27-1 -> 0.011511779

Sheet Definitions
B3: Unit | C3: Unit of Measure
B4: $ | C4: United States Dollar
B5: % | C5: Percent
B6: A$ | C6: Australian Dollar
B7: C$ | C7: Canadian Dollar
B8: gram | C8: Metric Gram
B9: ounce | C9: Troy Ounce
B10: pound | C10: United States Pound
B11: tonne | C11: Metric Ton
B12: Abbreviation | C12: Description
B13: AISC (1) | C13: All-In Sustaining Costs
B14: ARC | C14: Asset Retirement Cost
... B59: Heap Leaching | C59: Used when ore is low grade. Process. (1) Ore is crushed.

Sheet Key Questions
B2: $M
B5: What gold price is implicitly required to justify current market cap at a mid cycle multiple?
B6: Model | D6: Notes
B7: MC | C7: =+Main!K6 -> 121669.85
B8: Net Cash | C8: =+Main!K7-Main!K8 -> 3926
B9: EV | C9: =+C7-C8 -> 117743.85
B10: Needed FCF | C10: =+C9/7 -> 16820.55 | D10: assumes ~7x fcf
B11: FY25 Gold Sold | C11: =SUM(Model!#REF!) -> #REF!
B12: Sustaining AISC | C12: =AVERAGE(1651,1593,1566) -> 1603.3333
B14: FCF Per Oz Needed | C14: =+(C10/C11) * 1000 -> #REF!
B15: Gold price - $1.603/oz = $2,854/oz
B16: Required Gold Price | C16: =+C12+C14 -> #REF! | D16: If gold can stay above $4,000, business will naturally strengthen
B18: Average of current realized Godl Prices | C18: =AVERAGE(Model!#REF!) -> #REF!
B19: Current LBMA Price | C19: 4251.7 | D19: 46010
B20: Revenue Price Lag | C20: =+C19-C18 -> #REF!
B22: Incremental Rev | C22: =+(C11*C20) / 10^3 -> #REF!
B23: Incremental Margin | C23: 0.75
B24: After tax Conversion | C24: 0.7
B25: Incremental FCF | C25: =+C22*C23*C24 -> #REF!
B27: Adjusted FCF | C27: =+SUM(Model!#REF!,'Key Questions'!C25) -> #REF! | D27: overtime 4Q FCF should approach thise as Godl stays around $4k/oz
B28: Capex Normalization (Post Buildouts) | C28: 1500

Sheet Geology
B2: Reading Material
B3: Reserves and Resources
B4: 2024
B5: =+B4-1 -> 2023
B6: =+B5-1 -> 2022
B7: =+B6-1 -> 2021
B8: =+B7-1 -> 2020
B9: =+B8-1 -> 2019
B10: =+B9-1 -> 2018
B11: =+B10-1 -> 2017
B12: =+B11-1 -> 2016
B13: =+B12-1 -> 2015
B16: Lifecycle of a Mine
B17: Mining Process
B18: What we Mine

Sheet Operations
B9: Africa Asia Pacific
B10: Africa
B11: Ahafo North, Ghana
B12: Ahafo South, Ghana
B13: Australia
B14: Boddington, Australia
B15: Cadia, Australia
B16: Tanami, Australia
B17: Papua New Guinea
B18: Lihir, Papua New Guinea
B19: Americas
B20: Canada
... B32: Health and Safety
