Workbook

Sheet Main
B3: CEO | C3: William T Dillard II | F3: P | G3: 579
B4: CFO | F4: Class A | G4: =11.633238 -> 11.633238 | H4: Q126
F5: Class B | G5: =3.986233 -> 3.986233
F6: MC | G6: =G3 * sum(G4:G5) -> 9043.6737
F7: C | G7: =1157.662+259.743 -> 1417.405 | H7: =+H4 -> Q126
F8: D | G8: =96+225.701 -> 321.701 | H8: =+H7 -> Q126
F9: EV | G9: =+G6-G7+G8 -> 7947.9697
C14: Press Releases
C15: Q324

Sheet Model
C2: 45045 | D2: 45136 | E2: 45227 | F2: =+AF2 -> 45325 | G2: 45416 | H2: 45507 | I2: 45598 | AB2: 44226 | AC2: 43862 | AD2: 44587 | AE2: 44954 | AF2: 45325 | AG2: 45689 | AH2: 46053
C3: Q123 | D3: Q223 | E3: Q323 | F3: Q423 | G3: Q124 | H3: Q224 | I3: Q324 | J3: Q424 | K3: Q125 | L3: Q225 | M3: Q325 | N3: Q425 | O3: Q126 | P3: Q226 | Q3: Q326 | R3: Q426 | AA3: 2018 | AB3: 2019 | AC3: 2020 | AD3: 2021 | AE3: 2022 | AF3: 2023 | AG3: =+AF3+1 -> 2024 | AH3: =+AG3+1 -> 2025 | AI3: =+AH3+1 -> 2026 | AJ3: =+AI3+1 -> 2027 | AK3: =+AJ3+1 -> 2028 | AL3: =+AK3+1 -> 2029 | AM3: =+AL3+1 -> 2030 | AN3: =+AM3+1 -> 2031 | ... MC3: =+MB3+1 -> 2332
B4: SSS | O4: 0.03
B5: Store Count | C5: 274 | D5: 274 | E5: 273 | F5: =+AF5 -> 273 | G5: 274 | H5: 273 | I5: 273 | J5: 272 | O5: 272 | AD5: 280 | AE5: 277 | AF5: 273 | AG5: 272
B6: Retail sales/sqft | C6: 33 | D6: 33 | E6: 31 | F6: =+AF6-SUM(C6:E6) -> 46 | G6: 33 | H6: 31 | I6: 30 | O6: 46.1 | AD6: 138 | AE6: 146 | AF6: 143
B8: Sales | C8: 1583.948 | D8: 1567.377 | E8: 1476.362 | F8: =+AF8-SUM(C8:E8) -> 2124.366 | G8: 1549.051 | H8: 1489.938 | I8: 1427.009 | J8: 2016.6 | K8: 1528.9 | L8: 1513.8 | M8: 1513.8 | N8: =AH8-sum(K8:M8) -> 1917.123 | O8: =1568.427 -> 1568.427 | AA8: 6356.109 | AB8: 6203.52 | AC8: 4300.895 | AD8: 6492.993 | AE8: 6871.081 | AF8: 6752.053 | AG8: 6482.636 | AH8: 6473.623 | AI8: =+AH8*0.96 -> 6214.6781 | AJ8: =+AI8*0.96 -> 5966.091 | AK8: =+AJ8*0.96 -> 5727.4473 | AL8: =+AK8*0.96 -> 5498.3494 | AM8: =+AL8*0.96 -> 5278.4154 | AN8: =+AM8*0.96 -> 5067.2788 | AO8: =+AN8*0.96 -> 4864.5877 | AP8: =+AO8*0.96 -> 4670.0042 | ... AR8: =+AQ8*0.96 -> 4303.8758
B9: Services/Other | C9: 29.959 | D9: 30.041 | E9: 27.872 | F9: =+AF9-SUM(C9:E9) -> 34.495 | G9: 23.758 | H9: 24.708 | I9: 24.151 | J9: 35 | K9: 18.1 | L9: 22.2 | N9: =AH9-sum(K9:M9) -> 49.413 | O9: =20.194 -> 20.194 | AA9: 147.24 | AB9: 139.691 | AC9: 132.29 | AD9: 131.274 | AE9: 125.134 | AF9: 122.367 | AG9: 107.595 | AH9: 89.713 | AI9: =+AI8*(AH9/AH8) -> 86.12448 | AJ9: =+AJ8*(AI9/AI8) -> 82.679501 | AK9: =+AK8*(AJ9/AJ8) -> 79.372321 | AL9: =+AL8*(AK9/AK8) -> 76.197428 | AM9: =+AM8*(AL9/AL8) -> 73.149531 | AN9: =+AN8*(AM9/AM8) -> 70.22355 | AO9: =+AO8*(AN9/AN8) -> 67.414608 | AP9: =+AP8*(AO9/AO8) -> 64.718023 | ... AR9: =+AR8*(AQ9/AQ8) -> 59.64413
B10: Total Revenue | C10: =+SUM(C8:C9) -> 1613.907 | D10: =+SUM(D8:D9) -> 1597.418 | E10: =+SUM(E8:E9) -> 1504.234 | F10: =+SUM(F8:F9) -> 2158.861 | G10: =+SUM(G8:G9) -> 1572.809 | H10: =+SUM(H8:H9) -> 1514.646 | I10: =+SUM(I8:I9) -> 1451.16 | J10: =+SUM(J8:J9) -> 2051.6 | ... O10: =+SUM(O8:O9) -> 1588.621 | AA10: =+SUM(AA8:AA9) -> 6503.349 | AB10: =+SUM(AB8:AB9) -> 6343.211 | AC10: =+SUM(AC8:AC9) -> 4433.185 | AD10: =+SUM(AD8:AD9) -> 6624.267 | AE10: =+SUM(AE8:AE9) -> 6996.215 | AF10: =+SUM(AF8:AF9) -> 6874.42 | AG10: =SUM(AG8:AG9) -> 6590.231 | AH10: =SUM(AH8:AH9) -> 6563.336 | AI10: =SUM(AI8:AI9) -> 6300.8026 | AJ10: =SUM(AJ8:AJ9) -> 6048.7705 | AK10: =SUM(AK8:AK9) -> 5806.8196 | AL10: =SUM(AL8:AL9) -> 5574.5469 | AM10: =SUM(AM8:AM9) -> 5351.565 | AN10: =SUM(AN8:AN9) -> 5137.5024 | ... AR10: =SUM(AR8:AR9) -> 4363.52
B11: C | C11: 891.261 | D11: 958.835 | E11: 834.537 | F11: =+AF11-SUM(C11:E11) -> 1346.475 | G11: 857.825 | H11: 930.331 | I11: 819.313 | J11: 1312.1 | K11: 857.7 | L11: 959.306 | M11: 831.643 | N11: =AH11-sum(K11:M11) -> 1268.213 | O11: 870.368 | AA11: 4291.52 | AB11: 4235.978 | AC11: 3069.063 | AD11: 3747.665 | AE11: 3983.598 | AF11: 4031.108 | AG11: 3919.549 | AH11: 3916.862 | AI11: =+AI$10*(AH11/AH$10) -> 3760.1875 | AJ11: =+AJ$10*(AI11/AI$10) -> 3609.78 | AK11: =+AK$10*(AJ11/AJ$10) -> 3465.3888 | AL11: =+AL$10*(AK11/AK$10) -> 3326.7733 | AM11: =+AM$10*(AL11/AL$10) -> 3193.7023 | AN11: =+AN$10*(AM11/AM$10) -> 3065.9542 | AO11: =+AO$10*(AN11/AN$10) -> 2943.3161 | AP11: =+AP$10*(AO11/AO$10) -> 2825.5834 | ... AR11: =+AR$10*(AQ11/AQ$10) -> 2604.0577
B12: SG&A | C12: 406.375 | D12: 412.543 | E12: 421.825 | F12: =+AF12-SUM(C12:E12) -> 476.672 | G12: 426.674 | H12: 433.659 | I12: 418.899 | J12: 452 | K12: 421.7 | L12: 434.165 | M12: 440.409 | N12: =AH12-sum(K12:M12) -> 462.962 | O12: 443.98 | AA12: 1691.18 | AB12: 1691.017 | AC12: 1211.483 | AD12: 1536.554 | AE12: 1674.317 | AF12: 1717.415 | AG12: 1731.234 | AH12: 1759.236 | AI12: =+AI$10*(AH12/AH$10) -> 1688.8666 | AJ12: =+AJ$10*(AI12/AI$10) -> 1621.3119 | AK12: =+AK$10*(AJ12/AJ$10) -> 1556.4594 | AL12: =+AL$10*(AK12/AK$10) -> 1494.201 | AM12: =+AM$10*(AL12/AL$10) -> 1434.433 | AN12: =+AN$10*(AM12/AM$10) -> 1377.0557 | AO12: =+AO$10*(AN12/AN$10) -> 1321.9735 | AP12: =+AP$10*(AO12/AO$10) -> 1269.0945 | ... AR12: =+AR$10*(AQ12/AQ$10) -> 1169.5975
B13: Rentals | C13: 4.381 | D13: 4.961 | E13: 4.932 | F13: =+AF13-SUM(C13:E13) -> 7.295 | G13: 5.24 | H13: 4.956 | I13: 4.888 | J13: 6.5 | K13: 4.6 | L13: 4.551 | M13: 4.354 | N13: =AH13-sum(K13:M13) -> 5.718 | O13: 3.889 | AA13: 28.646 | AB13: 26.375 | AC13: 22.174 | AD13: 22.594 | AE13: 23.169 | AF13: 21.569 | AG13: 21.419 | AH13: 19.223 | AI13: =+AI$10*(AH13/AH$10) -> 18.45408 | AJ13: =+AJ$10*(AI13/AI$10) -> 17.715917 | AK13: =+AK$10*(AJ13/AJ$10) -> 17.00728 | AL13: =+AL$10*(AK13/AK$10) -> 16.326989 | AM13: =+AM$10*(AL13/AL$10) -> 15.673909 | AN13: =+AN$10*(AM13/AM$10) -> 15.046953 | AO13: =+AO$10*(AN13/AN$10) -> 14.445075 | AP13: =+AP$10*(AO13/AO$10) -> 13.867272 | ... AR13: =+AR$10*(AQ13/AQ$10) -> 12.780078
B14: Interest/Debt | C14: 0.123 | D14: 0.132 | E14: -1.79 | F14: =+AF14-SUM(C14:E14) -> -3.065 | G14: -3.532 | H14: -3.934 | I14: -4.478 | J14: -1.8 | K14: -0.8 | L14: -1.457 | M14: -3.076 | N14: =AH14-sum(K14:M14) -> -0.897 | O14: -0.699 | AA14: 52.518 | AB14: 46.227 | AC14: 49.108 | AD14: 43.092 | AE14: 30.527 | AF14: -4.6 | AG14: -13.695 | AH14: -6.23 | AI14: =+AI$10*(AH14/AH$10) -> -5.9808 | AJ14: =+AJ$10*(AI14/AI$10) -> -5.741568 | AK14: =+AK$10*(AJ14/AJ$10) -> -5.5119053 | AL14: =+AL$10*(AK14/AK$10) -> -5.2914291 | AM14: =+AM$10*(AL14/AL$10) -> -5.0797719 | AN14: =+AN$10*(AM14/AM$10) -> -4.876581 | AO14: =+AO$10*(AN14/AN$10) -> -4.6815178 | AP14: =+AP$10*(AO14/AO$10) -> -4.4942571 | ... AR14: =+AR$10*(AQ14/AQ$10) -> -4.1419073
B15: Other | C15: 4.698 | D15: 4.698 | E15: 4.697 | F15: =+AF15-SUM(C15:E15) -> 4.698 | G15: 6.158 | H15: 6.158 | I15: 6.158 | J15: 6.2 | K15: 5.7 | L15: 5.035 | M15: 5.035 | N15: =AH15-sum(K15:M15) -> 5.027 | O15: 5.003 | AA15: 7.66 | AB15: 7.667 | AC15: 8.417 | AD15: 11.366 | AE15: 7.744 | AF15: 18.791 | AG15: 24.631 | AH15: 20.797 | AI15: =+AI$10*(AH15/AH$10) -> 19.96512 | AJ15: =+AJ$10*(AI15/AI$10) -> 19.166515 | AK15: =+AK$10*(AJ15/AJ$10) -> 18.399855 | AL15: =+AL$10*(AK15/AK$10) -> 17.66386 | AM15: =+AM$10*(AL15/AL$10) -> 16.957306 | AN15: =+AN$10*(AM15/AM$10) -> 16.279014 | AO15: =+AO$10*(AN15/AN$10) -> 15.627853 | AP15: =+AP$10*(AO15/AO$10) -> 15.002739 | ... AR15: =+AR$10*(AQ15/AQ$10) -> 13.826524
B16: EBT | C16: =+C10-SUM(C11:C15) -> 307.069 | D16: =+D10-SUM(D11:D15) -> 216.249 | E16: =+E10-SUM(E11:E15) -> 240.033 | F16: =+AF16-SUM(C16:E16) -> 326.786 | G16: =+G10-SUM(G11:G15) -> 280.444 | H16: =+H10-SUM(H11:H15) -> 143.476 | I16: =+I10-SUM(I11:I15) -> 206.38 | J16: =+J10-SUM(J11:J15) -> 276.6 | K16: =+K10-SUM(K11:K15) -> 258.1 | L16: =+L10-SUM(L11:L15) -> 134.4 | M16: =+M10-SUM(M11:M15) -> 235.435 | N16: =+N10-SUM(N11:N15) -> 225.513 | O16: =+O10-SUM(O11:O15) -> 266.08 | AA16: =+AA10-SUM(AA11:AA15) -> 431.825 | AB16: =+AB10-SUM(AB11:AB15) -> 335.947 | AC16: =+AC10-SUM(AC11:AC15) -> 72.94 | AD16: =+AD10-SUM(AD11:AD15) -> 1262.996 | AE16: =+AE10-SUM(AE11:AE15) -> 1276.86 | AF16: =+AF10-SUM(AF11:AF15) -> 1090.137 | AG16: =+AG10-SUM(AG11:AG15) -> 907.093 | AH16: =+AH10-SUM(AH11:AH15) -> 853.448 | ... AR16: =+AR10-SUM(AR11:AR15) -> 567.40008
B17: Taxes | C17: 61.62 | D17: 40.08 | E17: 44.04 | F17: =+AF17-SUM(C17:E17) -> 32.03 | G17: 54.77 | H17: 22.63 | I17: 37.91 | J17: 20.9 | K17: 49.9 | L17: 21.75 | M17: 39 | N17: =AH17-sum(K17:M17) -> 14.05 | O17: 76.78 | AA17: 37.73 | AB17: 22.81 | AC17: -81.75 | AD17: 225.89 | AE17: 217.83 | AF17: 177.77 | AG17: 136.225 | AH17: 124.7 | AI17: =+AI16*(AH17/AH16) -> 119.712 | AJ17: =+AJ16*(AI17/AI16) -> 114.92352 | AK17: =+AK16*(AJ17/AJ16) -> 110.32658 | AL17: =+AL16*(AK17/AK16) -> 105.91352 | AM17: =+AM16*(AL17/AL16) -> 101.67698 | AN17: =+AN16*(AM17/AM16) -> 97.609896 | AO17: =+AO16*(AN17/AN16) -> 93.705501 | AP17: =+AP16*(AO17/AO16) -> 89.95728 | ... AR17: =+AR16*(AQ17/AQ16) -> 82.90463
B18: Net Income | C18: =+C16-C17 -> 245.449 | D18: =+D16-D17 -> 176.169 | E18: =+E16-E17 -> 195.993 | F18: =+AF18-SUM(C18:E18) -> 294.756 | G18: =+G16-G17 -> 225.674 | H18: =+H16-H17 -> 120.846 | I18: =+I16-I17 -> 168.47 | J18: =+J16-J17 -> 255.7 | K18: =+K16-K17 -> 208.2 | L18: =+L16-L17 -> 112.65 | M18: =+M16-M17 -> 196.435 | N18: =+N16-N17 -> 211.463 | O18: =+O16-O17 -> 189.3 | AA18: =+AA16-AA17 -> 394.095 | AB18: =+AB16-AB17 -> 313.137 | AC18: =+AC16-AC17 -> 154.69 | AD18: =+AD16-AD17 -> 1037.106 | AE18: =+AE16-AE17 -> 1059.03 | AF18: =+AF16-AF17 -> 912.367 | AG18: =+AG16-AG17 -> 770.868 | AH18: =+AH16-AH17 -> 728.748 | ... AR18: =+AR16-AR17 -> 484.49545 | AS18: =+AR18* ( 1 + $AU$30) -> 479.6505 | AT18: =+AS18* ( 1 + $AU$30) -> 474.85399 | AU18: =+AT18* ( 1 + $AU$30) -> 470.10545 | AV18: =+AU18* ( 1 + $AU$30) -> 465.4044 | AW18: =+AV18* ( 1 + $AU$30) -> 460.75036 | AX18: =+AW18* ( 1 + $AU$30) -> 456.14285 | AY18: =+AX18* ( 1 + $AU$30) -> 451.58142 | AZ18: =+AY18* ( 1 + $AU$30) -> 447.06561 | ... MC18: =+MB18* ( 1 + $AU$30) -> 24.48739
B19: EPS | C19: 11.85 | D19: 7.98 | E19: 9.49 | F19: =+AF19-SUM(C19:E19) -> 15.41 | G19: 11.09 | H19: 4.59 | I19: 7.73 | J19: 13.48 | K19: 10.39 | L19: 4.66 | M19: 8.31 | N19: =AH19-sum(K19:M19) -> 13.06 | O19: 16.04 | AA19: 6.23 | AB19: 4.38 | AC19: -3.16 | AD19: 41.88 | AE19: 50.81 | AF19: 44.73 | AG19: 36.82 | AH19: 36.42 | AI19: =+AI18/AI20 -> 34.9632 | AJ19: =+AJ18/AJ20 -> 33.564672 | AK19: =+AK18/AK20 -> 32.222085 | AL19: =+AL18/AL20 -> 30.933202 | AM19: =+AM18/AM20 -> 29.695874 | AN19: =+AN18/AN20 -> 28.508039 | AO19: =+AO18/AO20 -> 27.367717 | AP19: =+AP18/AP20 -> 26.273008 | ... AR19: =+AR18/AR20 -> 24.213205
B20: Shares | C20: =+C18/C19 -> 20.712996 | D20: =+D18/D19 -> 22.076316 | E20: =+E18/E19 -> 20.652582 | F20: =+F18/F19 -> 19.127579 | G20: =+G18/G19 -> 20.349324 | H20: =+H18/H19 -> 26.328105 | I20: =+I18/I19 -> 21.794308 | J20: =+J18/J19 -> 18.968843 | ... O20: =+O18/O19 -> 11.801746 | AA20: =AA18/AA19 -> 63.257624 | AB20: =AB18/AB19 -> 71.492466 | AC20: =AC18/AC19 -> -48.952532 | AD20: =AD18/AD19 -> 24.763754 | AE20: =AE18/AE19 -> 20.842944 | AF20: =AF18/AF19 -> 20.397205 | AG20: =AG18/AG19 -> 20.936122 | AH20: =AH18/AH19 -> 20.009555 | AI20: =+AH20 -> 20.009555 | AJ20: =+AI20 -> 20.009555 | AK20: =+AJ20 -> 20.009555 | AL20: =+AK20 -> 20.009555 | AM20: =+AL20 -> 20.009555 | AN20: =+AM20 -> 20.009555 | AO20: =+AN20 -> 20.009555 | AP20: =+AO20 -> 20.009555 | ... AR20: =+AQ20 -> 20.009555
B22: Growth Y/Y
B23: Sales | G23: =+G8/C8-1 -> -0.022031658 | H23: =+H8/D8-1 -> -0.049406748 | I23: =+I8/E8-1 -> -0.033428793 | J23: =+J8/F8-1 -> -0.050728547 | K23: =+K8/G8-1 -> -0.01300861 | L23: =+L8/H8-1 -> 0.016015432 | M23: =+M8/I8-1 -> 0.060820219 | N23: =+N8/J8-1 -> -0.049329069 | O23: =+O8/K8-1 -> 0.025853228 | AB23: =+AB8/AA8-1 -> -0.024006668 | AC23: =+AC8/AB8-1 -> -0.30670087 | AD23: =+AD8/AC8-1 -> 0.50968415 | AE23: =+AE8/AD8-1 -> 0.058230157 | AF23: =+AF8/AE8-1 -> -0.017323038 | AG23: =+AG8/AF8-1 -> -0.039901494 | AH23: =+AH8/AG8-1 -> -0.0013903295 | AI23: =+AI8/AH8-1 -> -0.04 | ... AR23: =+AR8/AQ8-1 -> -0.04
B24: Services/Other | G24: =+G9/C9-1 -> -0.20698288 | H24: =+H9/D9-1 -> -0.17752405 | I24: =+I9/E9-1 -> -0.13350316 | J24: =+J9/F9-1 -> 0.014639803 | K24: =+K9/G9-1 -> -0.23815136 | L24: =+L9/H9-1 -> -0.10150559 | M24: =+M9/I9-1 -> -1 | N24: =+N9/J9-1 -> 0.4118 | O24: =+O9/K9-1 -> 0.11569061 | AB24: =+AB9/AA9-1 -> -0.051270035 | AC24: =+AC9/AB9-1 -> -0.052981223 | AD24: =+AD9/AC9-1 -> -0.0076800968 | AE24: =+AE9/AD9-1 -> -0.0467724 | AF24: =+AF9/AE9-1 -> -0.022112296 | AG24: =+AG9/AF9-1 -> -0.12071882 | AH24: =+AH9/AG9-1 -> -0.16619731 | AI24: =+AI9/AH9-1 -> -0.04 | ... AR24: =+AR9/AQ9-1 -> -0.04
B25: Total Revenue | G25: =+G10/C10-1 -> -0.025464912 | H25: =+H10/D10-1 -> -0.051816118 | I25: =+I10/E10-1 -> -0.035283074 | J25: =+J10/F10-1 -> -0.04968407 | K25: =+K10/G10-1 -> -0.016409494 | L25: =+L10/H10-1 -> 0.014098344 | M25: =+M10/I10-1 -> 0.043165468 | N25: =+N10/J10-1 -> -0.041462273 | O25: =+O10/K10-1 -> 0.026904331 | AB25: =+AB10/AA10-1 -> -0.024623928 | AC25: =+AC10/AB10-1 -> -0.30111343 | AD25: =+AD10/AC10-1 -> 0.49424556 | AE25: =+AE10/AD10-1 -> 0.056149307 | AF25: =+AF10/AE10-1 -> -0.017408699 | AG25: =+AG10/AF10-1 -> -0.041340069 | AH25: =+AH10/AG10-1 -> -0.0040810406 | AI25: =+AI10/AH10-1 -> -0.04 | ... AR25: =+AR10/AQ10-1 -> -0.04
B26: Gross Margin | C26: =(C10-C11)/C10 -> 0.44776186 | D26: =(D10-D11)/D10 -> 0.39975949 | E26: =(E10-E11)/E10 -> 0.44520799 | F26: =(F10-F11)/F10 -> 0.37630306 | G26: =(G10-G11)/G10 -> 0.45459048 | H26: =(H10-H11)/H10 -> 0.38577661 | I26: =(I10-I11)/I10 -> 0.43540823 | J26: =(J10-J11)/J10 -> 0.36045038 | ... O26: =(O10-O11)/O10 -> 0.45212357 | AA26: =(AA10-AA11)/AA10 -> 0.34010615 | AB26: =(AB10-AB11)/AB10 -> 0.33220289 | AC26: =(AC10-AC11)/AC10 -> 0.30770699 | AD26: =(AD10-AD11)/AD10 -> 0.43425212 | AE26: =(AE10-AE11)/AE10 -> 0.43060669 | AF26: =(AF10-AF11)/AF10 -> 0.41360755 | AG26: =(AG10-AG11)/AG10 -> 0.40524862 | AH26: =(AH10-AH11)/AH10 -> 0.40322086 | ... AR26: =(AR10-AR11)/AR10 -> 0.40322086
C27: =+C16/C10 -> 0.19026437 | D27: =+D16/D10 -> 0.13537408 | E27: =+E16/E10 -> 0.15957158 | F27: =+F16/F10 -> 0.15136963 | G27: =+G16/G10 -> 0.17830773 | H27: =+H16/H10 -> 0.094725764 | I27: =+I16/I10 -> 0.14221726 | J27: =+J16/J10 -> 0.1348216 | ... O27: =+O16/O10 -> 0.16749118 | AA27: =+AA16/AA10 -> 0.066400404 | AB27: =+AB16/AB10 -> 0.052961662 | AC27: =+AC16/AC10 -> 0.016453182 | AD27: =+AD16/AD10 -> 0.190662 | AE27: =+AE16/AE10 -> 0.18250726 | AF27: =+AF16/AF10 -> 0.15857876 | AG27: =+AG16/AG10 -> 0.13764206 | AH27: =+AH16/AH10 -> 0.13003265 | ... AR27: =+AR16/AR10 -> 0.13003265
B30: Net Cash | D30: =+SUM(D31,D33) - SUM(D47) -> 603.087 | E30: =+SUM(E31,E33) - SUM(E47) -> 571.824 | F30: =+SUM(F31,F33) - SUM(F47) -> 634.862 | G30: =+SUM(G31,G33) - SUM(G47) -> 843.338 | H30: =+SUM(H31,H33) - SUM(H47) -> 748.965 | I30: =+SUM(I31,I33) - SUM(I47) -> 787.726 | J30: =+SUM(J31,J33) - SUM(J47) -> 722 | K30: =+SUM(K31,K33) - SUM(K47) -> 837.4 | AB30: =SUM(AB31,AB33)-AB44-AB47-AB51 -> -442.06 | AC30: =SUM(AC31,AC33)-AC44-AC47-AC51 -> -288.632 | AD30: =SUM(AD31,AD33)-AD44-AD47-AD51 -> -205.51 | AE30: =SUM(AE31,AE33)-AE44-AE47-AE51 -> 150.712 | AF30: =SUM(AF31,AF33)-AF44-AF47-AF51 -> 434.862 | AG30: =SUM(AG31,AG33)-AG44-AG47-AG51 -> 522 | AH30: =+K30 -> 837.4 | AI30: =+AH30*1.01 -> 845.774 | AJ30: =+AI30*1.01 -> 854.23174 | AK30: =+AJ30*1.01 -> 862.77406 | AL30: =+AK30*1.01 -> 871.4018 | AM30: =+AL30*1.01 -> 880.11582 | AN30: =+AM30*1.01 -> 888.91697 | AO30: =+AN30*1.01 -> 897.80614 | AP30: =+AO30*1.01 -> 906.78421 | ... AR30: =+AQ30*1.01 -> 925.01057 | AT30: Terminal | AU30: -0.01
B31: Cash | D31: 774.343 | E31: 842.001 | F31: 808.287 | G31: 817.825 | H31: 946.728 | I31: 980.392 | J31: 717.9 | K31: 900.5 | AB31: 123.509 | AC31: 277.077 | AD31: 360.339 | AE31: 716.759 | AF31: 808.287 | AG31: =+J31 -> 717.9 | AH31: =+K31 -> 900.5 | AT31: Discount | AU31: 0.07
B32: A/R | D32: 59.701 | E32: 57.412 | F32: 60.547 | G32: 49.251 | H32: 64.468 | I32: 61.741 | J32: 55.7 | K32: 56.9 | AB32: 49.853 | AC32: 46.16 | AD32: 36.693 | AE32: 39.777 | AF32: 60.547 | AG32: =+J32 -> 55.7 | AH32: =+K32 -> 56.9 | AT32: Total Equity Value | AU32: {=NPV(AU31,AI18:MC18)} -> 7258.392
B33: Investments | D33: 150.151 | E33: 51.257 | F33: 148.036 | G33: 347 | H33: 123.751 | I33: 128.875 | J33: 325.7 | K33: 258.5 | AB33: 0 | AC33: 0 | AD33: 0 | AE33: 0 | AF33: 148.036 | AG33: =+J33 -> 325.7 | AH33: =+K33 -> 258.5 | AT33: Shares | AU33: =sum(Main!G4:G5) -> 15.619471
B34: Inventories | D34: 1192.703 | E34: 1629.245 | F34: 1093.999 | G34: 1387.684 | H34: 1191.432 | I34: 1682.217 | J34: 1172 | K34: 1469.3 | AB34: 1528.417 | AC34: 1465.007 | AD34: 1087.763 | AE34: 1080.178 | AF34: 1093.999 | AG34: =+J34 -> 1172 | AH34: =+K34 -> 1469.3 | AT34: Estimate | AU34: =+AU32/AU33 -> 464.70152
B35: Fed/State I/T | D35: 0 | G35: 0 | H35: 35.462 | J35: 0 | K35: 0 | AB35: 0 | AC35: 0 | AD35: 118.439 | AE35: 118.439 | AF35: 0 | AG35: =+J35 -> 0 | AH35: =+K35 -> 0 | AT35: Current | AU35: =+Main!G3 -> 579
B36: OCA | D36: 103.331 | E36: 85.646 | F36: 97.341 | G36: 106.241 | H36: 91.701 | I36: 89.076 | J36: 96.8 | K36: 82.9 | AB36: 68.753 | AC36: 59.838 | AD36: 58.706 | AE36: 58.706 | AF36: 97.341 | AG36: =+J36 -> 96.8 | AH36: =+K36 -> 82.9 | AT36: Upside | AU36: =+AU34/AU35-1 -> -0.1974067
B37: PPE | D37: 1098.947 | E37: 1094.587 | F37: 1074.304 | G37: 1062.993 | H37: 1044.866 | I37: 1030.69 | J37: 1002.2 | K37: 976 | AB37: 1586.733 | AC37: 1458.176 | AD37: 1289.302 | AE37: 1074.304 | AF37: 1074.304 | AG37: =+J37 -> 1002.2 | AH37: =+K37 -> 976
B38: Op L | D38: 30.364 | E38: 34.462 | F38: 42.681 | G38: 41.909 | H38: 38.936 | I38: 35.921 | J38: 33.6 | K38: 32.5 | AB38: 0 | AC38: 47.924 | AD38: 47.612 | AE38: 42.681 | AF38: 42.681 | AG38: =+J38 -> 33.6 | AH38: =+K38 -> 32.5
B39: Deferred I/T | D39: 45.98 | E39: 47.563 | F39: 63.951 | G39: 64.017 | H39: 63.935 | I39: 64.733 | J39: 69.1 | K39: 71.3 | AB39: 0 | AC39: 0 | AD39: 23.453 | AE39: 63.951 | AF39: 63.951 | AG39: =+J39 -> 69.1 | AH39: =+K39 -> 71.3
B40: OA | D40: 56.842 | E40: 55.761 | F40: 59.76 | G40: 60.072 | H40: 60.583 | I40: 59.417 | J40: 58.1 | K40: 59.1 | AB40: 74.104 | AC40: 76.075 | AD40: 70.208 | AE40: 68.883 | AF40: 59.76 | AG40: =+J40 -> 58.1 | AH40: =+K40 -> 59.1 | AT40: EV/25E | AU40: =+Main!G6 / AH18 -> 12.409878
B41: Total Assets | D41: =+SUM(D31:D40) -> 3512.362 | E41: =+SUM(E31:E40) -> 3897.934 | F41: =+SUM(F31:F40) -> 3448.906 | G41: =+SUM(G31:G40) -> 3936.992 | H41: =+SUM(H31:H40) -> 3661.862 | I41: =+SUM(I31:I40) -> 4133.062 | J41: =+SUM(J31:J40) -> 3531.1 | K41: =+SUM(K31:K40) -> 3907 | AB41: =+SUM(AB31:AB40) -> 3431.369 | AC41: =+SUM(AC31:AC40) -> 3430.257 | AD41: =+SUM(AD31:AD40) -> 3092.515 | AE41: =+SUM(AE31:AE40) -> 3263.678 | AF41: =+SUM(AF31:AF40) -> 3448.906 | AG41: =+SUM(AG31:AG40) -> 3531.1 | AH41: =+SUM(AH31:AH40) -> 3907 | AT41: EV/26E | AU41: =+Main!G6 / AI18 -> 12.926956
B43: Trade A/P | D43: 803.142 | E43: 1181.198 | F43: 782.545 | G43: 1031.325 | H43: 768.758 | I43: 1214.982 | J43: 795 | K43: 1056.7 | AB43: 921.205 | AC43: 892.789 | AD43: 758.363 | AE43: 886.233 | AF43: 782.545 | AG43: =+J43 -> 795 | AH43: =+K43 -> 1056.7
B44: Curr debt | AB44: 0 | AC44: 0 | AE44: 44.8
B45: Current Op L | D45: 8.047 | E45: 8.461 | F45: 11.252 | G45: 11.596 | H45: 11.535 | I45: 11.721 | J45: 11.4 | K45: 10.8 | AB45: 1.214 | AC45: =1.219+14.654 -> 15.873 | AD45: 13.819 | AE45: 11.712 | AF45: 11.252 | AG45: =+J45 -> 11.4 | AH45: =+K45 -> 10.8 | AT45: EV/25R | AU45: =+Main!G9 / AH10 -> 1.2109649
B46: Fed/State I/T | D46: 115.633 | E46: 12.5 | F46: 33.959 | G46: 87.369 | H46: 0 | I46: 10.03 | J46: 28.5 | K46: 79.3 | AB46: 11.116 | AC46: 22.158 | AD46: 0.695 | AE46: 23.441 | AF46: 33.959 | AG46: =+J46 -> 28.5 | AH46: =+K46 -> 79.3 | AT46: EV / BV | AU46: =+Main!G9 / I52 -> 4.0480747
B47: LTD | D47: 321.407 | E47: 321.434 | F47: 321.461 | G47: 321.487 | H47: 321.514 | I47: 321.541 | J47: 321.6 | K47: 321.6 | AB47: 365.569 | AC47: 365.709 | AD47: 365.849 | AE47: 321.247 | AF47: 321.461 | AG47: =+J47 -> 321.6 | AH47: =+K47 -> 321.6
B48: Op L | D48: 22.291 | E48: 26.246 | F48: 31.728 | G48: 30.297 | H48: 27.44 | I48: 24.338 | J48: 22.3 | K48: 21.5 | AB48: 1.666 | AC48: =0.695+32.683 -> 33.378 | AD48: 33.392 | AE48: 30.969 | AF48: 31.728 | AG48: =+J48 -> 22.3 | AH48: =+K48 -> 21.5
B49: OL | D49: 332.326 | E49: 334.457 | F49: 370.893 | G49: 380.09 | H49: 383.694 | I49: 387.055 | J49: 356.1 | K49: 359.2 | AB49: 238.731 | AC49: 273.601 | AD49: 279.389 | AE49: 275.937 | AF49: 370.893 | AG49: =+J49 -> 356.1 | AH49: =+K49 -> 359.2
B50: Deferred i/t | AB50: 13.487 | AC50: 3.49
B51: Subordinated Deb | D51: 200 | E51: 200 | F51: 200 | G51: 200 | H51: 200 | I51: 200 | J51: 200 | K51: 200 | AB51: 200 | AC51: 200 | AD51: 200 | AE51: 200 | AF51: 200 | AG51: =+J51 -> 200 | AH51: =+K51 -> 200
B52: E | D52: 1709.516 | E52: 1813.638 | F52: 1697.068 | G52: 1874.992 | H52: 1948.921 | I52: 1963.395 | J52: 1796.2 | K52: 1857.9 | AB52: 1678.381 | AC52: 1623.259 | AD52: 1441.008 | AE52: 1451.218 | AF52: 1697.068 | AG52: =+J52 -> 1796.2 | AH52: =+K52 -> 1857.9
B53: TL + E | D53: =+SUM(D43:D52) -> 3512.362 | E53: =+SUM(E43:E52) -> 3897.934 | F53: =+SUM(F43:F52) -> 3448.906 | G53: =+SUM(G43:G52) -> 3937.156 | H53: =+SUM(H43:H52) -> 3661.862 | I53: =+SUM(I43:I52) -> 4133.062 | J53: =+SUM(J43:J52) -> 3531.1 | K53: =+SUM(K43:K52) -> 3907 | AB53: =+SUM(AB43:AB52) -> 3431.369 | AC53: =+SUM(AC43:AC52) -> 3430.257 | AD53: =+SUM(AD43:AD52) -> 3092.515 | AE53: =+SUM(AE43:AE52) -> 3245.557 | AF53: =+SUM(AF43:AF52) -> 3448.906 | AG53: =+J53 -> 3531.1 | AH53: =+K53 -> 3907
B55: Total Debt | D55: =SUM(D44,D47,D51) -> 521.407 | E55: =SUM(E44,E47,E51) -> 521.434 | F55: =SUM(F44,F47,F51) -> 521.461 | G55: =SUM(G44,G47,G51) -> 521.487 | H55: =SUM(H44,H47,H51) -> 521.514 | I55: =SUM(I44,I47,I51) -> 521.541 | J55: =SUM(J44,J47,J51) -> 521.6 | K55: =SUM(K44,K47,K51) -> 521.6 | AB55: =SUM(AB44,AB47,AB51) -> 565.569 | AC55: =SUM(AC44,AC47,AC51) -> 565.709 | AD55: =SUM(AD44,AD47,AD51) -> 565.849 | AE55: =SUM(AE44,AE47,AE51) -> 566.047 | AF55: =SUM(AF44,AF47,AF51) -> 521.461 | AG55: =SUM(AG44,AG47,AG51) -> 521.6
B56: Total Capital | D56: =+D55+D52 -> 2230.923 | E56: =+E55+E52 -> 2335.072 | F56: =+F55+F52 -> 2218.529 | G56: =+G55+G52 -> 2396.479 | H56: =+H55+H52 -> 2470.435 | I56: =+I55+I52 -> 2484.936 | J56: =+J55+J52 -> 2317.8 | K56: =+K55+K52 -> 2379.5 | AB56: =+AB55+AB52 -> 2243.95 | AC56: =+AC55+AC52 -> 2188.968 | AD56: =+AD55+AD52 -> 2006.857 | AE56: =+AE55+AE52 -> 2017.265 | AF56: =+AF55+AF52 -> 2218.529 | AG56: =+AG55+AG52 -> 2317.8
B57: Debt to Capital | D57: =+D55/D56 -> 0.23371806 | E57: =+E55/E56 -> 0.22330532 | F57: =+F55/F56 -> 0.23504809 | G57: =+G55/G56 -> 0.2176055 | H57: =+H55/H56 -> 0.21110209 | I57: =+I55/I56 -> 0.20988106 | J57: =+J55/J56 -> 0.22504099 | K57: =+K55/K56 -> 0.21920572 | AB57: =+AB55/AB56 -> 0.25204171 | AC57: =+AC55/AC56 -> 0.2584364 | AD57: =+AD55/AD56 -> 0.28195781 | AE57: =+AE55/AE56 -> 0.28060121 | AF57: =+AF55/AF56 -> 0.23504809 | AG57: =+AG55/AG56 -> 0.22504099
B58: Cash to Debt | D58: =SUM(D31,D33)/D55 -> 1.7730755 | E58: =SUM(E31,E33)/E55 -> 1.7130797 | F58: =SUM(F31,F33)/F55 -> 1.8339301 | G58: =SUM(G31,G33)/G55 -> 2.2336607 | H58: =SUM(H31,H33)/H55 -> 2.0526371 | I58: =SUM(I31,I33)/I55 -> 2.1269028 | J58: =SUM(J31,J33)/J55 -> 2.0007669 | K58: =SUM(K31,K33)/K55 -> 2.2220092 | AB58: =SUM(AB31,AB33)/AB55 -> 0.21838007 | AC58: =SUM(AC31,AC33)/AC55 -> 0.48978715 | AD58: =SUM(AD31,AD33)/AD55 -> 0.63681123 | AE58: =SUM(AE31,AE33)/AE55 -> 1.2662535 | AF58: =SUM(AF31,AF33)/AF55 -> 1.8339301 | AG58: =SUM(AG31,AG33)/AG55 -> 2.0007669
B62: CFFO | C62: 280.948 | D62: =397.85-C62 -> 116.902 | E62: =447.107-SUM(C62:D62) -> 49.257 | F62: =883.59-SUM(C62:E62) -> 436.483 | G62: 244.378 | H62: =175.957-G62 -> -68.421 | I62: =349.434-SUM(G62:H62) -> 173.477 | J62: =714.1-SUM(G62:I62) -> 364.666 | K62: 232.6 | AA62: 367.288 | AB62: 365.074 | AC62: 252.946 | AD62: 1280.02 | AE62: 948.391 | AF62: 883.59
B63: Capex | C63: -32.348 | D63: =+-63.807-C63 -> -31.459 | E63: =+-104.679-SUM(C63:D63) -> -40.872 | F63: =+-132.944-SUM(C63:E63) -> -28.265 | G63: -35.175 | H63: =+-61.086-G63 -> -25.911 | I63: =+-89.147-SUM(G63:H63) -> -28.061 | J63: =+-104.6-SUM(G63:I63) -> -15.453 | K63: -16.8 | AA63: -137.064 | AB63: -103.383 | AC63: -60.453 | AD63: -104.36 | AE63: -120.105 | AF63: -132.944
B64: Free Cash Flow | C64: =+SUM(C62:C63) -> 248.6 | D64: =+SUM(D62:D63) -> 85.443 | E64: =+SUM(E62:E63) -> 8.385 | F64: =+SUM(F62:F63) -> 408.218 | G64: =+SUM(G62:G63) -> 209.203 | H64: =+SUM(H62:H63) -> -94.332 | I64: =+SUM(I62:I63) -> 145.416 | J64: =+SUM(J62:J63) -> 349.213 | K64: =+SUM(K62:K63) -> 215.8 | AA64: =+SUM(AA62:AA63) -> 230.224 | AB64: =+SUM(AB62:AB63) -> 261.691 | AC64: =+SUM(AC62:AC63) -> 192.493 | AD64: =+SUM(AD62:AD63) -> 1175.66 | AE64: =+SUM(AE62:AE63) -> 828.286 | AF64: =+SUM(AF62:AF63) -> 750.646
B65: Net Income | C65: =+C18 -> 245.449 | D65: =+D18 -> 176.169 | E65: =+E18 -> 195.993 | F65: =+F18 -> 294.756 | G65: =+G18 -> 225.674 | H65: =+H18 -> 120.846 | I65: =+I18 -> 168.47 | J65: =+J18 -> 255.7 | K65: =+K18 -> 208.2 | AA65: =+AA18 -> 394.095 | AB65: =+AB18 -> 313.137 | AC65: =+AC18 -> 154.69 | AD65: =+AD18 -> 1037.106 | AE65: =+AE18 -> 1059.03 | AF65: =+AF18 -> 912.367
B67: 4QFCF | F67: =+SUM(C64:F64) -> 750.646 | G67: =+SUM(D64:G64) -> 711.249 | H67: =+SUM(E64:H64) -> 531.474 | I67: =+SUM(F64:I64) -> 668.505 | J67: =+SUM(G64:J64) -> 609.5 | K67: =+SUM(H64:K64) -> 616.097
B68: 4QNI | F68: =+SUM(C65:F65) -> 912.367 | G68: =+SUM(D65:G65) -> 892.592 | H68: =+SUM(E65:H65) -> 837.269 | I68: =+SUM(F65:I65) -> 809.746 | J68: =+SUM(G65:J65) -> 770.69 | K68: =+SUM(H65:K65) -> 753.216
AE69: =1^6 * 1^3 -> 1

Sheet Debt
