Workbook

Sheet Main
O2: Capital | W2: Debt to Capital | AE2: Cash to Debt
B3: Company | C3: Ticker | D3: Price | E3: Shares | F3: MC | G3: Cash | H3: Debt | I3: EV | J3: LastQ | K3: Next E Date | L3: Discount | M3: NPV | N3: Status | O3: 2019 | P3: =+O3+1 -> 2020 | Q3: =+P3+1 -> 2021 | R3: =+Q3+1 -> 2022 | S3: =+R3+1 -> 2023 | T3: =+S3+1 -> 2024 | U3: =+T3+1 -> 2025 | V3: =+U3+1 -> 2026 | W3: 2019 | X3: =+W3+1 -> 2020 | Y3: =+X3+1 -> 2021 | Z3: =+Y3+1 -> 2022 | AA3: =+Z3+1 -> 2023 | AB3: =+AA3+1 -> 2024 | AC3: =+AB3+1 -> 2025 | AD3: =+AC3+1 -> 2026 | AE3: 2019 | AF3: =+AE3+1 -> 2020 | AG3: =+AF3+1 -> 2021 | AH3: =+AG3+1 -> 2022 | AI3: =+AH3+1 -> 2023 | AJ3: =+AI3+1 -> 2024 | AK3: =+AJ3+1 -> 2025 | AL3: =+AK3+1 -> 2026 | AM3: Notes | AN3: Q124 | AO3: Q224 | AP3: Q324 | AQ3: Q424 | AR3: Q125 | AS3: Q225
B4: Dillards | C4: DDS | D4: 532.7 | E4: =11.651202+3.986233 -> 15.637435 | F4: =+D4*E4 -> 8330.0616 | G4: 900.504 | H4: =321.594+200 -> 521.594 | I4: =+F4-G4+H4 -> 7951.1516 | J4: Q225 | K4: 45883 | L4: 0.08 | M4: 7455 | N4: Beat | O4: 2243.95 | P4: 2188.968 | Q4: 2006.857 | R4: 2017.265 | S4: 2218.529 | T4: 2317.8 | U4: 2380 | W4: 0.25204171 | X4: 0.2584364 | Y4: 0.28195781 | Z4: 0.28060121 | AA4: 0.23504809 | AB4: 0.22504099 | AC4: 0.22 | AE4: 0.21838007 | AF4: 0.48978715 | AG4: 0.63681123 | AH4: 1.2662535 | AI4: 1.8339301 | AJ4: 2.0007669 | AK4: 2.22 | AN4: Beat | AO4: Miss | AP4: Beat | AQ4: Beat | AR4: Beat | AS4: Beat
B5: Macy's | C5: M | D5: 15 | E5: 271.53953 | F5: =+D5*E5 -> 4073.0929 | G5: 932 | H5: =6+2774 -> 2780 | I5: =+F5-G5+H5 -> 5921.0929 | J5: Q225 | K5: 45903 | L5: 0.08 | M5: 2203 | O5: 11187 | P5: 10537 | Q5: 7412 | R5: 7078 | S5: 7033 | T5: 7331 | U5: 7231 | W5: 0.42468937 | X5: 0.39479928 | Y5: 0.65555855 | Z5: 0.42328341 | AA5: 0.42627613 | AB5: 0.37907516 | AC5: 0.38 | AE5: 0.24458009 | AF5: 0.16466346 | AG5: 0.34554435 | AH5: 0.28771696 | AI5: 0.3448966 | AJ5: 0.46995322 | AK5: 0.34 | AN5: Beat | AO5: Beat | AP5: Beat | AQ5: Beat | AR5: Beat
B6: Kohl's | C6: KSS | D6: 13.89 | E6: 112 | F6: =+D6*E6 -> 1555.68 | G6: 153 | H6: 2072 | I6: =+F6-G6+H6 -> 3474.68 | J6: V | K6: 45896 | L6: 0.1 | M6: 2115 | N6: Beat | O6: 7567 | P6: 7354 | Q6: 7647 | R6: 5760 | S6: 5623 | T6: 5616 | U6: 5851 | W6: 0.26959165 | X6: 0.25890672 | Y6: 0.32051785 | Z6: 0.34670139 | AA6: 0.30766495 | AB6: 0.32336715 | AC6: 0.3541275 | AE6: 0.45784314 | AF6: 0.37972689 | AG6: 0.92656059 | AH6: 0.076614922 | AI6: 0.10578035 | AJ6: 0.073747936 | AK6: 0.07 | AN6: Miss | AO6: Beat | AP6: Beat | AQ6: Beat | AR6: Beat | AS6: Beat
B8: Private
B9: Nordstrom | C9: JWN | AM9: 2025 taken private by Nordstrom family and El Puerto de Liverpool
B10: Belk | AM10: 2015 taken private by Sycamore Partners
B12: Bankrupt / Restructured
B13: JcPenney | C13: JCP | D13: 0.13 | G13: 386 | H13: 3721 | O13: 4550 | W13: =+H13/O13 -> 0.8178022 | AE13: =+G13/H13 -> 0.10373555 | AM13: 2020 bankrupcy, restructured as Catalyst Brands
B14: Sears | C14: SHLDC | AM14: 2018 bankruptcy but still trades pink sheets, privately owned by Transformco
B16: Defunct/Absorbed
B17: Marshall Field's | AM17: 2006 Absorbed into Macy's
B18: Filene's | AM18: 2006 Absorbed into Macy's
B19: Wanamaker's | AM19: 1995 Absorbed into Hecht's, then Macy's
B20: Monthomery Ward | AM20: 2001 Liquidated 2001, brand revived online only
B21: Mervyn's | AM21: 2008 Bankrupt

Sheet Bonds
R1: =TODAY() -> 46206 | S1: 100
Q2: Returns
B3: Underlying | C3: Symbol | D3: CUSIP | E3: Type | F3: Coupon | G3: Issue Date | H3: Maturity | I3: Callable | J3: Years | K3: Price | L3: Post 20% rally | M3: S&P | N3: S&P Last R | O3: Moody | P3: Moody Last R | Q3: Coupons | R3: Capital Gain | S3: Total Return $ | T3: Return | U3: IRR | V3: Curr Yield
B4: SHLD | C4: SHLDQ3675201 | D4: 812404408 | E4: ELN | F4: 0.07 | H4: 52062 | J4: =(H4-$R$1)/365 -> 16.043836
B5: JCP | D5: 708130AD1 | F5: 0.0565 | G5: 40322 | H5: 43983 | J5: =(H5-$R$1)/365 -> -6.090411 | K5: 0.173 | O5: WR
B6: JCP | D6: 708160CB0 | F6: 0.05875 | G6: 42544 | H6: 45108 | J6: =(H6-$R$1)/365 -> -3.0082192 | K6: 0.173 | O6: WR
B7: JCP | D7: USU7083NAB74 | F7: 0.05875 | G7: 42544 | H7: 45108 | J7: =(H7-$R$1)/365 -> -3.0082192 | K7: 8
B8: JCP | D8: 708160CF1 | F8: 0 | G8: 42544 | H8: 45108 | J8: =(H8-$R$1)/365 -> -3.0082192 | K8: 3 | O8: C
B9: JCP | D9: 708160BE5 | F9: 0.07125 | G9: 34296 | H9: 45245 | J9: =(H9-$R$1)/365 -> -2.6328767 | K9: 3
B10: JCP | D10: USU7083NAC57 | F10: 0.08625 | G10: 43171 | H10: 45731 | J10: =(H10-$R$1)/365 -> -1.3013699 | K10: 0.395 | O10: WR
B11: JCP | D11: 708160CD6 | F11: 0.08625 | G11: 43171 | H11: 45731 | J11: =(H11-$R$1)/365 -> -1.3013699 | K11: 0.395 | O11: C
B12: JCP | D12: 708160BK1 | F12: 0.069 | G12: 35296 | H12: 46249 | J12: =(H12-$R$1)/365 -> 0.11780822 | K12: 1 | O12: C
B13: JCP | D13: 708160BR6 | F13: 0 | G13: 35534 | H13: 46478 | J13: =(H13-$R$1)/365 -> 0.74520548 | K13: 1 | O13: C
B14: JCP | D14: 708130AC3 | F14: 0.06375 | G14: 43948 | H14: 45214 | J14: =(H14-$R$1)/365 -> -2.7178082 | K14: 0.7 | O14: C
B15: JCP | D15: 708130BS4 | F15: 7.4 | G15: 35534 | H15: 50131 | J15: =(H15-$R$1)/365 -> 10.753425 | K15: 0.7 | O15: C
B16: JCP | D16: 708160BL9 | F16: 7.625 | G16: 35486 | H16: 72015 | J16: =(H16-$R$1)/365 -> 70.709589 | K16: 6.95 | O16: C
B17: KSS | C17: KSS.GI | D17: 500255AQ7 | E17: Corp | F17: 0.06875 | H17: 50389 | I17: N | J17: =(H17-$R$1)/365 -> 11.460274 | K17: 68.83 | M17: BB- | N17: 45645 | O17: B3 | P17: 45790 | Q17: =+(F17*$S$1) * J17 -> 78.789384 | R17: =($S$1-K17) -> 31.17 | S17: =SUM(Q17:R17) -> 109.95938 | T17: =+S17/$K17 -> 1.5975502 | U17: =IFERROR(YIELD($R$1,H17,F17,K17,$S$1,2,0), "") -> 0.11936589 | V17: =+IFERROR((F17*$S$1)/K17, "") -> 0.099883772
B18: KSS | C18: KSS.GG | D18: 500255AN4 | E18: Corp | F18: 0.06 | H18: 48594 | I18: N | J18: =(H18-$R$1)/365 -> 6.5424658 | K18: 72.5 | M18: BB- | N18: 45645 | O18: B3 | P18: 45790 | Q18: =+(F18*$S$1) * J18 -> 39.254795 | R18: =($S$1-K18) -> 27.5 | S18: =SUM(Q18:R18) -> 66.754795 | T18: =+S18/$K18 -> 0.92075579 | U18: =IFERROR(YIELD($R$1,H18,F18,K18,$S$1,2,0), "") -> 0.12232666 | V18: =+IFERROR((F18*$S$1)/K18, "") -> 0.082758621
B19: KSS | C19: KSS4268838 | D19: 500255AV6 | E19: Corp | F19: 0.0555 | H19: 53160 | I19: Y | J19: =(H19-$R$1)/365 -> 19.052055 | K19: 61.125 | M19: BB- | N19: 45645 | O19: B3 | P19: 45790 | Q19: =+(F19*$S$1) * J19 -> 105.7389 | R19: =($S$1-K19) -> 38.875 | S19: =SUM(Q19:R19) -> 144.6139 | T19: =+S19/$K19 -> 2.3658716 | U19: =IFERROR(YIELD($R$1,H19,F19,K19,$S$1,2,0), "") -> 0.10224444 | V19: =+IFERROR((F19*$S$1)/K19, "") -> 0.090797546
B20: KSS | C20: KSS5159081 | D20: 500255AX2 | E20: Corp | F20: 0.05125 | H20: 47969 | I20: Y | J20: =(H20-$R$1)/365 -> 4.830137 | K20: 79.5 | M20: BB- | N20: 45645 | O20: B3 | P20: 45790 | Q20: =+(F20*$S$1) * J20 -> 24.754452 | R20: =($S$1-K20) -> 20.5 | S20: =SUM(Q20:R20) -> 45.254452 | T20: =+S20/$K20 -> 0.56923839 | U20: =IFERROR(YIELD($R$1,H20,F20,K20,$S$1,2,0), "") -> 0.10663412 | V20: =+IFERROR((F20*$S$1)/K20, "") -> 0.064465409
B21: KSS | D21: USU5003PAC15 | E21: Corp | F21: 0.1 | H21: 47635 | J21: =(H21-$R$1)/365 -> 3.9150685 | K21: 107.1 | O21: Ba3 | Q21: =+(F21*$S$1) * J21 -> 39.150685 | R21: =($S$1-K21) -> -7.1 | S21: =SUM(Q21:R21) -> 32.050685 | T21: =+S21/$K21 -> 0.29925943 | U21: =IFERROR(YIELD($R$1,H21,F21,K21,$S$1,2,0), "") -> 0.0785229 | V21: =+IFERROR((F21*$S$1)/K21, "") -> 0.093370682
B22: M | C22: M.AJ | D22: 55616XAC1 | E22: Corp | F22: 0.07 | H22: 46798 | I22: N | J22: =(H22-$R$1)/365 -> 1.6219178 | K22: 107.1 | L22: 106.89 | M22: BB+ | N22: 44882 | O22: Ba2 | P22: 45740 | Q22: =+(F22*$S$1) * J22 -> 11.353425 | R22: =($S$1-K22) -> -7.1 | S22: =SUM(Q22:R22) -> 4.2534247 | T22: =+S22/$K22 -> 0.039714516 | U22: =IFERROR(YIELD($R$1,H22,F22,K22,$S$1,2,0), "") -> 0.024895407 | V22: =+IFERROR((F22*$S$1)/K22, "") -> 0.065359477
B23: M | C23: M4184487 | D23: 55616XAM9 | E23: Corp | F23: 0.045 | H23: 49293 | I23: Y | J23: =(H23-$R$1)/365 -> 8.4575342 | K23: 82.52 | L23: 83.75 | M23: BB+ | N23: 44882 | O23: Ba2 | P23: 45740 | Q23: =+(F23*$S$1) * J23 -> 38.058904 | R23: =($S$1-K23) -> 17.48 | S23: =SUM(Q23:R23) -> 55.538904 | T23: =+S23/$K23 -> 0.67303568 | U23: =IFERROR(YIELD($R$1,H23,F23,K23,$S$1,2,0), "") -> 0.073085816 | V23: =+IFERROR((F23*$S$1)/K23, "") -> 0.054532235
B24: M | C24: M.AA | D24: 55616XAG2 | E24: Corp | F24: 0.05125 | G24: 41287 | H24: 51881 | I24: Y | J24: =(H24-$R$1)/365 -> 15.547945 | K24: 72.992 | L24: 74.95 | M24: BB+ | N24: 44882 | O24: Ba2 | P24: 45740 | Q24: =+(F24*$S$1) * J24 -> 79.683219 | R24: =($S$1-K24) -> 27.008 | S24: =SUM(Q24:R24) -> 106.69122 | T24: =+S24/$K24 -> 1.4616837 | U24: =IFERROR(YIELD($R$1,H24,F24,K24,$S$1,2,0), "") -> 0.082379925 | V24: =+IFERROR((F24*$S$1)/K24, "") -> 0.070213174
B25: M | C25: M390952 | D25: 55616XAJ6 | E25: Corp | F25: 0.043 | G25: 41233 | H25: 52277 | I25: Y | J25: =(H25-$R$1)/365 -> 16.632877 | K25: 67.141 | L25: 73.35 | M25: BB+ | N25: 44882 | O25: Ba2 | P25: 45740 | Q25: =+(F25*$S$1) * J25 -> 71.52137 | R25: =($S$1-K25) -> 32.859 | S25: =SUM(Q25:R25) -> 104.38037 | T25: =+S25/$K25 -> 1.5546443 | U25: =IFERROR(YIELD($R$1,H25,F25,K25,$S$1,2,0), "") -> 0.078797242 | V25: =+IFERROR((F25*$S$1)/K25, "") -> 0.064044325
B26: M | D26: 314275AC2 | E26: Corp | F26: 0.06375 | G26: 39153 | H26: 50114 | J26: =(H26-$R$1)/365 -> 10.706849 | K26: 84.616 | L26: 86.104 | O26: Ba2 | P26: 45740 | Q26: =+(F26*$S$1) * J26 -> 68.256164 | R26: =($S$1-K26) -> 15.384 | S26: =SUM(Q26:R26) -> 83.640164 | T26: =+S26/$K26 -> 0.98846748 | U26: =IFERROR(YIELD($R$1,H26,F26,K26,$S$1,2,0), "") -> 0.086007166 | V26: =+IFERROR((F26*$S$1)/K26, "") -> 0.075340361
B27: M | D27: 5516XAM9 | E27: Corp | F27: 0.045 | G27: 41961 | H27: 49293 | J27: =(H27-$R$1)/365 -> 8.4575342 | K27: 82.552 | Q27: =+(F27*$S$1) * J27 -> 38.058904 | R27: =($S$1-K27) -> 17.448 | S27: =SUM(Q27:R27) -> 55.506904 | T27: =+S27/$K27 -> 0.67238715 | U27: =IFERROR(YIELD($R$1,H27,F27,K27,$S$1,2,0), "") -> 0.073028065 | V27: =+IFERROR((F27*$S$1)/K27, "") -> 0.054511096
B28: M | D28: USU5562LAF68 | E28: Corp | F28: 0.067 | G28: 44040 | H28: 49140 | J28: =(H28-$R$1)/365 -> 8.0383562 | K28: 87.813 | L28: 89.371 | O28: Ba2 | Q28: =+(F28*$S$1) * J28 -> 53.856986 | R28: =($S$1-K28) -> 12.187 | S28: =SUM(Q28:R28) -> 66.043986 | T28: =+S28/$K28 -> 0.75209805 | U28: =IFERROR(YIELD($R$1,H28,F28,K28,$S$1,2,0), "") -> 0.088509517 | V28: =+IFERROR((F28*$S$1)/K28, "") -> 0.076298498
B29: M | D29: USU5562LAJ80 | E29: Corp | F29: 0.06125 | G29: 44630 | H29: 48288 | J29: =(H29-$R$1)/365 -> 5.7041096 | K29: 97.7645 | L29: 99.642 | O29: Ba2 | Q29: =+(F29*$S$1) * J29 -> 34.937671 | R29: =($S$1-K29) -> 2.2355 | S29: =SUM(Q29:R29) -> 37.173171 | T29: =+S29/$K29 -> 0.38023179 | U29: =IFERROR(YIELD($R$1,H29,F29,K29,$S$1,2,0), "") -> 0.065993847 | V29: =+IFERROR((F29*$S$1)/K29, "") -> 0.062650553
B30: M | D30: USU5562LAH25 | E30: Corp | F30: 0.05875 | G30: 44630 | H30: 47557 | J30: =(H30-$R$1)/365 -> 3.7013699 | K30: 99.243 | L30: 99 | O30: Ba2 | Q30: =+(F30*$S$1) * J30 -> 21.745548 | R30: =($S$1-K30) -> 0.757 | S30: =SUM(Q30:R30) -> 22.502548 | T30: =+S30/$K30 -> 0.22674192 | U30: =IFERROR(YIELD($R$1,H30,F30,K30,$S$1,2,0), "") -> 0.06103412 | V30: =+IFERROR((F30*$S$1)/K30, "") -> 0.05919813
B31: M | D31: 31410HAQ4 | E31: Corp | F31: 0.069 | G31: 36325 | H31: 47209 | J31: =(H31-$R$1)/365 -> 2.7479452 | K31: 109 | O31: Ba2 | Q31: =+(F31*$S$1) * J31 -> 18.960822 | R31: =($S$1-K31) -> -9 | S31: =SUM(Q31:R31) -> 9.9608219 | T31: =+S31/$K31 -> 0.091383687 | U31: =IFERROR(YIELD($R$1,H31,F31,K31,$S$1,2,0), "") -> 0.034328756 | V31: =+IFERROR((F31*$S$1)/K31, "") -> 0.063302752
B32: DDS | D32: 254063AU4 | E32: Corp | F32: 0.0775 | G32: 39153 | H32: 46218 | J32: =(H32-$R$1)/365 -> 0.032876712 | K32: 101.817 | O32: Baa3 | Q32: =+(F32*$S$1) * J32 -> 0.25479452 | R32: =($S$1-K32) -> -1.817 | S32: =SUM(Q32:R32) -> -1.5622055 | T32: =+S32/$K32 -> -0.015343268 | U32: =IFERROR(YIELD($R$1,H32,F32,K32,$S$1,2,0), "") -> -0.4435016 | V32: =+IFERROR((F32*$S$1)/K32, "") -> 0.076116955
B33: DDS | D33: 254063AW0 | E33: Corp | F33: 0.0775 | G33: 35565 | H33: 46522 | J33: =(H33-$R$1)/365 -> 0.86575342 | K33: 104.262 | O33: Baa3 | Q33: =+(F33*$S$1) * J33 -> 6.709589 | R33: =($S$1-K33) -> -4.262 | S33: =SUM(Q33:R33) -> 2.447589 | T33: =+S33/$K33 -> 0.02347537 | U33: =IFERROR(YIELD($R$1,H33,F33,K33,$S$1,2,0), "") -> 0.027342325 | V33: =+IFERROR((F33*$S$1)/K33, "") -> 0.074331971
B34: DDS | D34: 254067AN1 | E34: Corp | F34: 0.07 | G34: 36136 | H34: 47088 | J34: =(H34-$R$1)/365 -> 2.4164384 | K34: 105.897 | O34: Baa3 | Q34: =+(F34*$S$1) * J34 -> 16.915068 | R34: =($S$1-K34) -> -5.897 | S34: =SUM(Q34:R34) -> 11.018068 | T34: =+S34/$K34 -> 0.10404514 | U34: =IFERROR(YIELD($R$1,H34,F34,K34,$S$1,2,0), "") -> 0.043932299 | V34: =+IFERROR((F34*$S$1)/K34, "") -> 0.066101967
N49: =100*16 -> 1600

Sheet M Curve
D8: =+Bonds!B3 -> Underlying | E8: =+Bonds!D3 -> CUSIP | F8: =+Bonds!H3 -> Maturity | G8: =+Bonds!F3 -> Coupon | H8: =+Bonds!U3 -> IRR | I8: Price
D9: M | E9: 55616XAC1 | F9: 46798 | G9: 0.07 | H9: 0.039466985 | I9: {=XLOOKUP(E9,Bonds!D:D,Bonds!K:K)} -> 107.1
D10: M | E10: 55616XAM9 | F10: 49293 | G10: 0.045 | H10: 0.070989482 | I10: {=XLOOKUP(E10,Bonds!D:D,Bonds!K:K)} -> 82.52
D11: M | E11: 55616XAG2 | F11: 51881 | G11: 0.05125 | H11: 0.081377607 | I11: {=XLOOKUP(E11,Bonds!D:D,Bonds!K:K)} -> 72.992
D12: M | E12: 55616XAJ6 | F12: 52277 | G12: 0.043 | H12: 0.077691499 | I12: {=XLOOKUP(E12,Bonds!D:D,Bonds!K:K)} -> 67.141
D13: M | E13: 314275AC2 | F13: 50114 | G13: 0.06375 | H13: 0.084906104 | I13: {=XLOOKUP(E13,Bonds!D:D,Bonds!K:K)} -> 84.616
D14: M | E14: 5516XAM9 | F14: 49293 | G14: 0.045 | H14: 0.070935992 | I14: {=XLOOKUP(E14,Bonds!D:D,Bonds!K:K)} -> 82.552
D15: M | E15: USU5562LAF68 | F15: 49140 | G15: 0.067 | H15: 0.086958411 | I15: {=XLOOKUP(E15,Bonds!D:D,Bonds!K:K)} -> 87.813
D16: M | E16: USU5562LAJ80 | F16: 48288 | G16: 0.06125 | H16: 0.065495373 | I16: {=XLOOKUP(E16,Bonds!D:D,Bonds!K:K)} -> 97.7645
D17: M | E17: USU5562LAH25 | F17: 47557 | G17: 0.05875 | H17: 0.060670294 | I17: {=XLOOKUP(E17,Bonds!D:D,Bonds!K:K)} -> 99.243
D18: M | E18: 31410HAQ4 | F18: 47209 | G18: 0.069 | H18: 0.041740475 | I18: {=XLOOKUP(E18,Bonds!D:D,Bonds!K:K)} -> 109
