Workbook

Sheet Main
B1: IR
B3: HQ: Denver, CO
B4: CEO | C4: Tom Palmer | J4: P | K4: 105 | N4: News | O4: Contains
B5: New CEO | C5: Natascha Viljoen's | J5: S | K5: 1091.263 | L5: Q325 | N5: 45632 | O5: selling Cripple Creek & Victor operation in Colorado to SSR Mining for up to $275m
B6: CFO | J6: MC | K6: =+K4*K5 -> 114582.61 | N6: 45621 | O6: selling Eleonore operation in Northern Quebec
J7: C | K7: =5639+4103 -> 9742 | L7: =+L5 -> Q325 | N7: 45614 | O7: selling Musselwhite operation in Ontario, Canada
B8: P * Q | J8: D | K8: 5180 | L8: =+L7 -> Q325 | N8: 45594 | O8: 1st battery ev large mining truck deployed in cripple creek colorado
B9: P: LBMA (Gold),LME (Cu), Timing | J9: EV | K9: =+K6-K7+K8 -> 110020.61 | N9: 45573 | O9: selling Akyem operation in Repub of Ghana to Zijin Mining Group
B10: Q: Production capability (mine capacity, mill throughput, weather), recovery (metallurgy/cil/heap effic, Ownership) | N10: 45568 | O10: announces Tom palmer as Internal council on Mining and Metald) ICMM chair
N11: 45588 | O11: Q4 guidance: 1.8m oz of gold
B12: Equity Method Investments | N12: 45497 | O12: annual prod guide: 6.9m oz
B13: Pueblo Viejo Mine (50%) | N13: 45407 | O13: reaffirmed guide
B14: NuevaUnion Project (50%)
B15: Lundin Gold (32%)
B16: Norte Abierto Project (50%) | N16: Press Releases
B17: Greatland (10%) | N17: 45953 | O17: Q325 results
N18: 45770 | O18: Q125 Results
N19: 45684 | O19: early redemption of 5.3% notes due 2026
N20: 45684 | O20: sale of porcupine operation for up $425m

Sheet Model
C2: Q122 | D2: Q222 | E2: Q322 | F2: Q422 | G2: Q123 | H2: Q223 | I2: Q323 | J2: Q423 | K2: Q124 | L2: Q224 | M2: Q324 | N2: Q424 | O2: Q125 | P2: Q225 | Q2: Q325 | R2: Q425 | W2: 2015 | X2: =+W2+1 -> 2016 | Y2: =+X2+1 -> 2017 | Z2: =+Y2+1 -> 2018 | AA2: 2019 | AB2: 2020 | AC2: 2021 | AD2: 2022 | AE2: 2023 | AF2: =+AE2+1 -> 2024 | AG2: =+AF2+1 -> 2025 | AH2: =+AG2+1 -> 2026 | AI2: =+AH2+1 -> 2027 | AJ2: =+AI2+1 -> 2028 | AK2: =+AJ2+1 -> 2029 | AL2: =+AK2+1 -> 2030 | AM2: =+AL2+1 -> 2031 | ... IG2: =+IF2+1 -> 2233
B3: LBMA Gold Price
B4: Low | W4: 1049 | X4: 1077 | Y4: 1151 | Z4: 1178 | AA4: 1270 | AB4: 1474 | AC4: 1684 | AD4: 1629 | AE4: 1811 | AF4: 1985 | AG4: 2636
B5: High | W5: 1296 | X5: 166 | Y5: 1346 | Z5: 1355 | AA5: 1546 | AB5: 2067 | AC5: 1943 | AD5: 2039 | AE5: 2078 | AF5: 2778 | AG5: 2928
B6: Mean | W6: 1160 | X6: 1251 | Y6: 1257 | Z6: 1268 | AA6: 1393 | AB6: 1770 | AC6: 1799 | AD6: 1800 | AE6: 1941 | AF6: 2386 | AG6: 2759
B7: Portfolio
B8: Boddington | K8: 142 | L8: 147 | M8: 137 | N8: 164 | O8: 126 | P8: 147 | Q8: 146 | AF8: =SUM(K8:N8) -> 590 | AG8: =SUM(O8:R8) -> 419
B9: Tanami | K9: 90 | L9: 99 | M9: 102 | N9: 117 | O9: 78 | P9: 90 | Q9: 100 | AF9: =SUM(K9:N9) -> 408 | AG9: =SUM(O9:R9) -> 268
B10: Cadia | K10: 122 | L10: 117 | M10: 115 | N10: 110 | O10: 103 | P10: 104 | Q10: 97 | AF10: =SUM(K10:N10) -> 464 | AG10: =SUM(O10:R10) -> 304
B11: Likir | K11: 181 | L11: 141 | M11: 129 | N11: 163 | O11: 164 | P11: 160 | Q11: 129 | AF11: =SUM(K11:N11) -> 614 | AG11: =SUM(O11:R11) -> 453
B12: Ahafo | K12: 190 | L12: 184 | M12: 213 | N12: 211 | O12: 205 | P12: 197 | Q12: 145 | AF12: =SUM(K12:N12) -> 798 | AG12: =SUM(O12:R12) -> 547
B13: Ahafo North | AF13: =SUM(K13:N13) -> 0 | AG13: =SUM(O13:R13) -> 0
B14: Penasquito | K14: 45 | L14: 64 | M14: 63 | N14: 127 | O14: 123 | P14: 148 | Q14: 88 | AF14: =SUM(K14:N14) -> 299 | AG14: =SUM(O14:R14) -> 359
B15: Cerro Negro | K15: 81 | L15: 19 | M15: 60 | N15: 78 | O15: 28 | P15: 42 | Q15: 68 | AF15: =SUM(K15:N15) -> 238 | AG15: =SUM(O15:R15) -> 138
B16: Yanacocha | K16: 91 | L16: 78 | M16: 93 | N16: 92 | O16: 105 | P16: 131 | Q16: 152 | AF16: =SUM(K16:N16) -> 354 | AG16: =SUM(O16:R16) -> 388
B17: Merian | K17: 57 | L17: 46 | M17: 43 | N17: 59 | O17: 47 | P17: 40 | Q17: 35 | AF17: =SUM(K17:N17) -> 205 | AG17: =SUM(O17:R17) -> 122
B18: Nrucejack | K18: 37 | L18: 60 | M18: 89 | N18: 72 | O18: 41 | P18: 50 | Q18: 79 | AF18: =SUM(K18:N18) -> 258 | AG18: =SUM(O18:R18) -> 170
B19: Red Chris | K19: 6 | L19: 9 | M19: 9 | N19: 16 | O19: 14 | P19: 15 | Q19: 15 | AF19: =SUM(K19:N19) -> 40 | AG19: =SUM(O19:R19) -> 44
B20: Nevada Gold Mines (38.5%) | K20: 264 | L20: 253 | M20: 242 | N20: 280 | O20: 216 | P20: 239 | Q20: 251 | AF20: =SUM(K20:N20) -> 1039 | AG20: =SUM(O20:R20) -> 706
B21: Oueblo Viejo (40%) | K21: 54 | L21: 53 | M21: 66 | N21: 62 | O21: 49 | P21: 63 | Q21: 72 | AF21: =SUM(K21:N21) -> 235 | AG21: =SUM(O21:R21) -> 184
B22: Fruta Del Norte (32%) | K22: 21 | L22: 35 | M22: 43 | N22: 39 | O22: 43 | P22: 38 | Q22: 44 | AF22: =SUM(K22:N22) -> 138 | AG22: =SUM(O22:R22) -> 125
B23: Total Tier 1 Portfolio Production | K23: =SUM(K8:K19,K20:K22) -> 1381 | L23: =SUM(L8:L19,L20:L22) -> 1305 | M23: =SUM(M8:M19,M20:M22) -> 1404 | N23: =SUM(N8:N19,N20:N22) -> 1590 | O23: =SUM(O8:O19,O20:O22) -> 1342 | P23: =SUM(P8:P19,P20:P22) -> 1464 | Q23: =SUM(Q8:Q19,Q20:Q22) -> 1421 | AF23: =SUM(K23:N23) -> 5680 | AG23: =SUM(O23:R23) -> 4227
B24: Non Core Assets | K24: 294 | L24: 302 | M24: 264 | N24: 309 | O24: 195 | P24: 14 | Q24: 0 | AF24: =SUM(K24:N24) -> 1169 | AG24: =SUM(O24:R24) -> 209
B25: Total Attributable Gold Production | K25: =SUM(K23:K24) -> 1675 | L25: =SUM(L23:L24) -> 1607 | M25: =SUM(M23:M24) -> 1668 | N25: =SUM(N23:N24) -> 1899 | O25: =SUM(O23:O24) -> 1537 | P25: =SUM(P23:P24) -> 1478 | Q25: =SUM(Q23:Q24) -> 1421 | AD25: 5956 | AE25: 5554 | AF25: =SUM(K25:N25) -> 6849 | AG25: =SUM(O25:R25) -> 4436
B27: Metal Sold
B28: Gold Oz Sold (koz) | G28: 1188 | H28: 1197 | I28: 1229 | J28: 1726 | K28: 1599 | L28: 1543 | M28: 1568 | N28: =+AF28-SUM(K28:M28) -> 1829 | O28: 1442 | P28: 1380 | Q28: 1319 | R28: 1600 | AD28: 5812 | AE28: 5420 | AF28: 6539 | AG28: =+AF28*1.05 -> 6865.95 | AH28: 6800 | AI28: 6800 | AJ28: 6800 | AK28: 6800 | AL28: 6800 | AM28: 6800 | AN28: 6800 | AO28: 6800 | AP28: 6800
B29: Copper Sold ($/lb) | K29: 80 | L29: 84 | M29: 77 | N29: =+AF29-SUM(K29:M29) -> 91 | O29: 76 | P29: 83 | Q29: 68 | R29: =+Q29*1.05 -> 71.4 | AD29: 85 | AE29: 155 | AF29: 332 | AG29: =+AF29*1.05 -> 348.6 | AH29: 400 | AI29: 400 | AJ29: 400 | AK29: 400 | AL29: 400 | AM29: 400 | AN29: 400 | AO29: 400 | AP29: 400
B30: Silver ($/moz) | K30: 10 | L30: 8 | M30: 6 | N30: =+AF30-SUM(K30:M30) -> 9 | O30: 6 | P30: 7 | Q30: 8 | R30: =+Q30*1.05 -> 8.4 | AD30: 30 | AE30: 17 | AF30: 33 | AG30: =+AF30*1.05 -> 34.65 | AH30: 40 | AI30: 40 | AJ30: 40 | AK30: 40 | AL30: 40 | AM30: 40 | AN30: 40 | AO30: 40 | AP30: 40
B31: Lead ($/lb) | K31: 65 | L31: 43 | M31: 36 | N31: =+AF31-SUM(K31:M31) -> 69 | O31: 47 | P31: 50 | Q31: 60 | R31: =+Q31*1.05 -> 63 | AD31: 147 | AE31: 107 | AF31: 213 | AG31: =+AF31*1.05 -> 223.65 | AH31: 200 | AI31: 200 | AJ31: 200 | AK31: 200 | AL31: 200 | AM31: 200 | AN31: 200 | AO31: 200 | AP31: 200
B32: Zinc ($/lb) | K32: 135 | L32: 113 | M32: 134 | N32: =+AF32-SUM(K32:M32) -> 163 | O32: 161 | P32: 124 | Q32: 149 | R32: =+Q32*1.05 -> 156.45 | AD32: 373 | AE32: 222 | AF32: 545 | AG32: =+AF32*1.05 -> 572.25 | AH32: 600 | AI32: 600 | AJ32: 600 | AK32: 600 | AL32: 600 | AM32: 600 | AN32: 600 | AO32: 600 | AP32: 600
B33: Average Realized Price | R33: 4325
B34: Gold ($/oz) | G34: 1906 | H34: 1965 | I34: 1920 | J34: 2004 | K34: 2090 | L34: 2347 | M34: 2518 | N34: 2643 | O34: 2944 | P34: 3320 | Q34: 3539 | R34: =+Q34 -> 3539 | AE34: 1954 | AF34: =+N34 -> 2643 | AG34: =+R34 -> 3539 | AH34: =+AG34*1.05 -> 3715.95 | AI34: =+AH34*1.05 -> 3901.7475 | AJ34: =+'Key Questions'!C16 -> 4341.0498 | AK34: =+AJ34 -> 4341.0498 | AL34: =+AK34 -> 4341.0498 | AM34: =+AL34 -> 4341.0498 | AN34: =+AM34 -> 4341.0498 | AO34: =+AN34 -> 4341.0498 | AP34: =+AO34 -> 4341.0498
B35: Copper ($/lb) | K35: 3.72 | L35: 4.47 | M35: 4.31 | N35: 3.57 | O35: 4.65 | P35: 4.37 | Q35: 4.67 | R35: =AVERAGE(O35:Q35) -> 4.5633333 | AF35: =+N35 -> 3.57 | AG35: =+R35 -> 4.5633333 | AH35: =+AG35*1.05 -> 4.7915 | AI35: =+AH35*1.05 -> 5.031075 | AJ35: =+AI35*1.05 -> 5.2826288 | AK35: =+AJ35*1.05 -> 5.5467602 | AL35: =+AK35*1.05 -> 5.8240982 | AM35: =+AL35 -> 5.8240982 | AN35: =+AM35 -> 5.8240982 | AO35: =+AN35 -> 5.8240982 | AP35: =+AO35 -> 5.8240982
B36: Silver ($/moz) | K36: 20.41 | L36: 26.2 | M36: 25.98 | N36: 25.15 | O36: 30.12 | P36: 29.5 | Q36: 37.02 | R36: =AVERAGE(O36:Q36) -> 32.213333 | AF36: =+N36 -> 25.15 | AG36: =+R36 -> 32.213333 | AH36: =+AG36*1.05 -> 33.824 | AI36: =+AH36*1.05 -> 35.5152 | AJ36: =+AI36*1.05 -> 37.29096 | AK36: =+AJ36*1.05 -> 39.155508 | AL36: =+AK36*1.05 -> 41.113283 | AM36: =+AL36 -> 41.113283 | AN36: =+AM36 -> 41.113283 | AO36: =+AN36 -> 41.113283 | AP36: =+AO36 -> 41.113283
B37: Lead ($/lb) | K37: 0.92 | L37: 1.05 | M37: 0.86 | N37: 0.86 | O37: 0.89 | P37: 0.88 | Q37: 0.86 | R37: =AVERAGE(O37:Q37) -> 0.87666667 | AF37: =+N37 -> 0.86 | AG37: =+R37 -> 0.87666667 | AH37: =+AG37*1.05 -> 0.9205 | AI37: =+AH37*1.05 -> 0.966525 | AJ37: =+AI37*1.05 -> 1.0148513 | AK37: =+AJ37*1.05 -> 1.0655938 | AL37: =+AK37*1.05 -> 1.1188735 | AM37: =+AL37 -> 1.1188735 | AN37: =+AM37 -> 1.1188735 | AO37: =+AN37 -> 1.1188735 | AP37: =+AO37 -> 1.1188735
B38: Zinc ($/lb) | K38: 0.92 | L38: 1.31 | M38: 1.14 | N38: 1.21 | O38: 1.13 | P38: 1.13 | Q38: 1.29 | R38: =AVERAGE(O38:Q38) -> 1.1833333 | AF38: =+N38 -> 1.21 | AG38: =+R38 -> 1.1833333 | AH38: =+AG38*1.05 -> 1.2425 | AI38: =+AH38*1.05 -> 1.304625 | AJ38: =+AI38*1.05 -> 1.3698563 | AK38: =+AJ38*1.05 -> 1.4383491 | AL38: =+AK38*1.05 -> 1.5102665 | AM38: =+AL38 -> 1.5102665 | AN38: =+AM38 -> 1.5102665 | AO38: =+AN38 -> 1.5102665 | AP38: =+AO38 -> 1.5102665
B40: Gold CAS ($/oz) | K40: 1057 | L40: 1152 | M40: 1207 | N40: 1096 | O40: 1227 | P40: 1215 | Q40: 1815 | AF40: 1126
B41: Gold AISC ($/oz) | K41: 1439 | L41: 1562 | M41: 1611 | N41: 1463 | O41: 1651 | P41: 1593 | Q41: 1566 | AF41: 1516
B43: Modeled Revenue
B44: Gold | L44: =+L28*L34/10^3 -> 3621.421 | M44: =+M28*M34/10^3 -> 3948.224 | O44: =+O28*O34/10^3 -> 4245.248 | P44: =+P28*P34/10^3 -> 4581.6 | Q44: =+Q28*Q34/10^3 -> 4667.941 | R44: =+R28*R34/10^3 -> 5662.4 | AG44: =SUM(O44:R44) -> 19157.189 | AH44: =+AH28*AH34/10^3 -> 25268.46 | AI44: =+AI28*AI34/10^3 -> 26531.883 | AJ44: =+AJ28*AJ34/10^3 -> 29519.139 | AK44: =+AK28*AK34/10^3 -> 29519.139 | AL44: =+AL28*AL34/10^3 -> 29519.139 | AM44: =+AM28*AM34/10^3 -> 29519.139 | AN44: =+AN28*AN34/10^3 -> 29519.139 | AO44: =+AO28*AO34/10^3 -> 29519.139 | AP44: =+AP28*AP34/10^3 -> 29519.139
B45: Copper | L45: =+L29*L35 -> 375.48 | M45: =+M29*M35 -> 331.87 | O45: =+O29*O35 -> 353.4 | P45: =+P29*P35 -> 362.71 | Q45: =+Q29*Q35 -> 317.56 | R45: =+R29*R35 -> 325.822 | AG45: =SUM(O45:R45) -> 1359.492 | AH45: =+AH29*AH35 -> 1916.6 | AI45: =+AI29*AI35 -> 2012.43 | AJ45: =+AJ29*AJ35 -> 2113.0515 | AK45: =+AK29*AK35 -> 2218.7041 | AL45: =+AL29*AL35 -> 2329.6393 | AM45: =+AM29*AM35 -> 2329.6393 | AN45: =+AN29*AN35 -> 2329.6393 | AO45: =+AO29*AO35 -> 2329.6393 | AP45: =+AP29*AP35 -> 2329.6393
B46: Silver | L46: =+L30*L36 -> 209.6 | M46: =+M30*M36 -> 155.88 | O46: =+O30*O36 -> 180.72 | P46: =+P30*P36 -> 206.5 | Q46: =+Q30*Q36 -> 296.16 | R46: =+R30*R36 -> 270.592 | AG46: =SUM(O46:R46) -> 953.972 | AH46: =+AH30*AH36 -> 1352.96 | AI46: =+AI30*AI36 -> 1420.608 | AJ46: =+AJ30*AJ36 -> 1491.6384 | AK46: =+AK30*AK36 -> 1566.2203 | AL46: =+AL30*AL36 -> 1644.5313 | AM46: =+AM30*AM36 -> 1644.5313 | AN46: =+AN30*AN36 -> 1644.5313 | AO46: =+AO30*AO36 -> 1644.5313 | AP46: =+AP30*AP36 -> 1644.5313
B47: Lead | L47: =+L31*L37 -> 45.15 | M47: =+M31*M37 -> 30.96 | O47: =+O31*O37 -> 41.83 | P47: =+P31*P37 -> 44 | Q47: =+Q31*Q37 -> 51.6 | R47: =+R31*R37 -> 55.23 | AG47: =SUM(O47:R47) -> 192.66 | AH47: =+AH31*AH37 -> 184.1 | AI47: =+AI31*AI37 -> 193.305 | AJ47: =+AJ31*AJ37 -> 202.97025 | AK47: =+AK31*AK37 -> 213.11876 | AL47: =+AL31*AL37 -> 223.7747 | AM47: =+AM31*AM37 -> 223.7747 | AN47: =+AN31*AN37 -> 223.7747 | AO47: =+AO31*AO37 -> 223.7747 | AP47: =+AP31*AP37 -> 223.7747
B48: Zinc | L48: =+L32*L38 -> 148.03 | M48: =+M32*M38 -> 152.76 | O48: =+O32*O38 -> 181.93 | P48: =+P32*P38 -> 140.12 | Q48: =+Q32*Q38 -> 192.21 | R48: =+R32*R38 -> 185.1325 | AG48: =SUM(O48:R48) -> 699.3925 | AH48: =+AH32*AH38 -> 745.5 | AI48: =+AI32*AI38 -> 782.775 | AJ48: =+AJ32*AJ38 -> 821.91375 | AK48: =+AK32*AK38 -> 863.00944 | AL48: =+AL32*AL38 -> 906.15991 | AM48: =+AM32*AM38 -> 906.15991 | AN48: =+AN32*AN38 -> 906.15991 | AO48: =+AO32*AO38 -> 906.15991 | AP48: =+AP32*AP38 -> 906.15991
B50: I/S
B51: Gold | C51: 2514 | D51: 2722 | E51: 2350 | F51: =+AD51-SUM(C51:E51) -> 2830 | G51: 2303 | H51: 2380 | I51: 2400 | J51: =+AE51-SUM(G51:I51) -> 3510 | K51: 3341 | L51: 3623 | M51: 3945 | N51: =+AF51-SUM(K51:M51) -> 4837 | O51: 4245 | P51: 4582 | Q51: 4669 | R51: =+R44 -> 5662.4 | AA51: 9049 | AB51: 10350 | AC51: 10543 | AD51: 10416 | AE51: 10593 | AF51: 15746 | AG51: =SUM(O51:R51) -> 19158.4 | AH51: =+AH44 -> 25268.46 | AI51: =+AI44 -> 26531.883 | AJ51: =+AJ44 -> 29519.139 | AK51: =+AK44 -> 29519.139 | AL51: =+AL44 -> 29519.139 | AM51: =+AM44 -> 29519.139 | AN51: =+AN44 -> 29519.139 | AO51: =+AO44 -> 29519.139 | AP51: =+AP44 -> 29519.139
B52: Copper | C52: 99 | D52: 76 | E52: 48 | F52: =+AD52-SUM(C52:E52) -> 93 | G52: 110 | H52: 82 | I52: 90 | J52: =+AE52-SUM(G52:I52) -> 293 | K52: 297 | L52: 377 | M52: 329 | N52: =+AF52-SUM(K52:M52) -> 324 | O52: 354 | P52: 360 | Q52: 319 | R52: =+R45 -> 325.822 | AA52: 210 | AB52: 155 | AC52: 295 | AD52: 316 | AE52: 575 | AF52: 1327 | AG52: =SUM(O52:R52) -> 1358.822 | AH52: =+AH45 -> 1916.6 | AI52: =+AI45 -> 2012.43 | AJ52: =+AJ45 -> 2113.0515 | AK52: =+AK45 -> 2218.7041 | AL52: =+AL45 -> 2329.6393 | AM52: =+AM45 -> 2329.6393 | AN52: =+AN45 -> 2329.6393 | AO52: =+AO45 -> 2329.6393 | AP52: =+AP45 -> 2329.6393
B53: Silver | C53: 156 | D53: 140 | E53: 105 | F53: =+AD53-SUM(C53:E53) -> 148 | G53: 117 | H53: 124 | I53: 5 | J53: =+AE53-SUM(G53:I53) -> 89 | K53: 201 | L53: 209 | M53: 147 | N53: =+AF53-SUM(K53:M53) -> 238 | O53: 188 | P53: 191 | Q53: 293 | R53: =+R46 -> 270.592 | AA53: 253 | AB53: 510 | AC53: 651 | AD53: 549 | AE53: 335 | AF53: 795 | AG53: =SUM(O53:R53) -> 942.592 | AH53: =+AH46 -> 1352.96 | AI53: =+AI46 -> 1420.608 | AJ53: =+AJ46 -> 1491.6384 | AK53: =+AK46 -> 1566.2203 | AL53: =+AL46 -> 1644.5313 | AM53: =+AM46 -> 1644.5313 | AN53: =+AN46 -> 1644.5313 | AO53: =+AO46 -> 1644.5313 | AP53: =+AP46 -> 1644.5313
B54: Lead | C54: 44 | D54: 28 | E54: 26 | F54: =+AD54-SUM(C54:E54) -> 35 | G54: 32 | H54: 32 | I54: 0 | J54: =+AE54-SUM(G54:I54) -> 32 | K54: 60 | L54: 44 | M54: 32 | N54: =+AF54-SUM(K54:M54) -> 59 | O54: 42 | P54: 43 | Q54: 52 | R54: =+R47 -> 55.23 | AA54: 85 | AB54: 134 | AC54: 172 | AD54: 133 | AE54: 96 | AF54: 195 | AG54: =SUM(O54:R54) -> 192.23 | AH54: =+AH47 -> 184.1 | AI54: =+AI47 -> 193.305 | AJ54: =+AJ47 -> 202.97025 | AK54: =+AK47 -> 213.11876 | AL54: =+AL47 -> 223.7747 | AM54: =+AM47 -> 223.7747 | AN54: =+AN47 -> 223.7747 | AO54: =+AO47 -> 223.7747 | AP54: =+AP47 -> 223.7747
B55: Zinc | C55: 210 | D55: 92 | E55: 105 | F55: =+AD55-SUM(C55:E55) -> 94 | G55: 117 | H55: 65 | I55: -2 | J55: =+AE55-SUM(G55:I55) -> 33 | K55: 124 | L55: 149 | M55: 152 | N55: =+AF55-SUM(K55:M55) -> 197 | O55: 181 | P55: 141 | Q55: 191 | R55: =+R48 -> 185.1325 | AA55: 143 | AB55: 348 | AC55: 561 | AD55: 501 | AE55: 213 | AF55: 622 | AG55: =SUM(O55:R55) -> 698.1325 | AH55: =+AH48 -> 745.5 | AI55: =+AI48 -> 782.775 | AJ55: =+AJ48 -> 821.91375 | AK55: =+AK48 -> 863.00944 | AL55: =+AL48 -> 906.15991 | AM55: =+AM48 -> 906.15991 | AN55: =+AN48 -> 906.15991 | AO55: =+AO48 -> 906.15991 | AP55: =+AP48 -> 906.15991
B56: Sales | C56: =SUM(C51:C55) -> 3023 | D56: =SUM(D51:D55) -> 3058 | E56: =+SUM(E51:E55) -> 2634 | F56: =SUM(F51:F55) -> 3200 | G56: =SUM(G51:G55) -> 2679 | H56: =SUM(H51:H55) -> 2683 | I56: =SUM(I51:I55) -> 2493 | J56: =SUM(J51:J55) -> 3957 | K56: =SUM(K51:K55) -> 4023 | L56: =SUM(L51:L55) -> 4402 | M56: =SUM(M51:M55) -> 4605 | ... R56: =SUM(R51:R55) -> 6499.1765 | AA56: =SUM(AA51:AA55) -> 9740 | AB56: =SUM(AB51:AB55) -> 11497 | AC56: =SUM(AC51:AC55) -> 12222 | AD56: =SUM(AD51:AD55) -> 11915 | AE56: =SUM(AE51:AE55) -> 11812 | AF56: =+SUM(AF51:AF55) -> 18685 | AG56: =+SUM(AG51:AG55) -> 22350.177 | AH56: =+SUM(AH51:AH55) -> 29467.62 | AI56: =+SUM(AI51:AI55) -> 30941.001 | AJ56: =+SUM(AJ51:AJ55) -> 34148.713 | AK56: =+SUM(AK51:AK55) -> 34380.191 | AL56: =+SUM(AL51:AL55) -> 34623.244 | AM56: =+SUM(AM51:AM55) -> 34623.244 | ... AP56: =+SUM(AP51:AP55) -> 34623.244
B57: Costs | C57: 1435 | D57: 1708 | E57: 1545 | F57: =+AD57-SUM(C57:E57) -> 1780 | G57: 1482 | H57: 1543 | I57: 1371 | J57: =+AE57-SUM(G57:I57) -> 2303 | K57: 2106 | L57: 2156 | M57: 2310 | N57: =+N$56*(M57/M$56) -> 2836.7101 | O57: 2106 | P57: 2001 | Q57: 1951 | R57: =+R$56*(Q57/Q$56) -> 2295.4188 | AA57: 5195 | AB57: 5014 | AC57: 5435 | AD57: 6468 | AE57: 6699 | AF57: =+SUM(K57:N57) -> 9408.7101 | AG57: =SUM(O57:R57) -> 8353.4188 | AH57: =+AH$56*(AG57/AG$56) -> 11013.576 | AI57: =+AI$56*(AH57/AH$56) -> 11564.255 | AJ57: =+AJ$56*(AI57/AI$56) -> 12763.143 | AK57: =+AK$56*(AJ57/AJ$56) -> 12849.659 | AL57: =+AL$56*(AK57/AK$56) -> 12940.5 | AM57: =+AM$56*(AL57/AL$56) -> 12940.5 | AN57: =+AN$56*(AM57/AM$56) -> 12940.5 | AO57: =+AO$56*(AN57/AN$56) -> 12940.5 | AP57: =+AP$56*(AO57/AO$56) -> 12940.5
B58: D&A | C58: 547 | D58: 559 | E58: 508 | F58: =+AD58-SUM(C58:E58) -> 571 | G58: 461 | H58: 486 | I58: 480 | J58: =+AE58-SUM(G58:I58) -> 681 | K58: 654 | L58: 602 | M58: 631 | N58: =+N$56*(M58/M$56) -> 774.87622 | O58: 593 | P58: 620 | Q58: 643 | R58: =+R$56*(Q58/Q$56) -> 756.51167 | AA58: 1960 | AB58: 2300 | AC58: 2323 | AD58: 2185 | AE58: 2108 | AF58: =+SUM(K58:N58) -> 2661.8762 | AG58: =SUM(O58:R58) -> 2612.5117 | AH58: =+AH$56*(AG58/AG$56) -> 3444.4695 | AI58: =+AI$56*(AH58/AH$56) -> 3616.693 | AJ58: =+AJ$56*(AI58/AI$56) -> 3991.6423 | AK58: =+AK$56*(AJ58/AJ$56) -> 4018.6999 | AL58: =+AL$56*(AK58/AK$56) -> 4047.1103 | AM58: =+AM$56*(AL58/AL$56) -> 4047.1103 | AN58: =+AN$56*(AM58/AM$56) -> 4047.1103 | AO58: =+AO$56*(AN58/AN$56) -> 4047.1103 | AP58: =+AP$56*(AO58/AO$56) -> 4047.1103
B59: Reclamation & Remediation | C59: 61 | D59: 49 | E59: 53 | F59: =+AD59-SUM(C59:E59) -> 758 | G59: 66 | H59: 66 | I59: 166 | J59: =+AE59-SUM(G59:I59) -> 1235 | K59: 98 | L59: 94 | M59: 132 | N59: =+N$56*(M59/M$56) -> 162.09772 | O59: 93 | P59: 83 | Q59: 123 | R59: =+R$56*(Q59/Q$56) -> 144.71374 | AA59: 280 | AB59: 366 | AC59: 1846 | AD59: 921 | AE59: 1533 | AF59: =+SUM(K59:N59) -> 486.09772 | AG59: =SUM(O59:R59) -> 443.71374 | AH59: =+AH$56*(AG59/AG$56) -> 585.01497 | AI59: =+AI$56*(AH59/AH$56) -> 614.26572 | AJ59: =+AJ$56*(AI59/AI$56) -> 677.94781 | AK59: =+AK$56*(AJ59/AJ$56) -> 682.54331 | AL59: =+AL$56*(AK59/AK$56) -> 687.36858 | AM59: =+AM$56*(AL59/AL$56) -> 687.36858 | AN59: =+AN$56*(AM59/AM$56) -> 687.36858 | AO59: =+AO$56*(AN59/AN$56) -> 687.36858 | AP59: =+AP$56*(AO59/AO$56) -> 687.36858
B60: Exploration | C60: 38 | D60: 62 | E60: 69 | F60: =+AD60-SUM(C60:E60) -> 62 | G60: 48 | H60: 66 | I60: 78 | J60: =+AE60-SUM(G60:I60) -> 73 | K60: 53 | L60: 57 | M60: 74 | N60: =+N$56*(M60/M$56) -> 90.872964 | O60: 49 | P60: 61 | Q60: 65 | R60: =+R$56*(Q60/Q$56) -> 76.474742 | AA60: 265 | AB60: 187 | AC60: 209 | AD60: 231 | AE60: 265 | AF60: =+SUM(K60:N60) -> 274.87296 | AG60: =SUM(O60:R60) -> 251.47474 | AH60: =+AH$56*(AG60/AG$56) -> 331.55721 | AI60: =+AI$56*(AH60/AH$56) -> 348.13507 | AJ60: =+AJ$56*(AI60/AI$56) -> 384.22689 | AK60: =+AK$56*(AJ60/AJ$56) -> 386.83139 | AL60: =+AL$56*(AK60/AK$56) -> 389.56611 | AM60: =+AM$56*(AL60/AL$56) -> 389.56611 | AN60: =+AN$56*(AM60/AM$56) -> 389.56611 | AO60: =+AO$56*(AN60/AN$56) -> 389.56611 | AP60: =+AP$56*(AO60/AO$56) -> 389.56611
B61: Advanced projects, R&D | C61: 44 | D61: 45 | E61: 80 | F61: =+AD61-SUM(C61:E61) -> 60 | G61: 35 | H61: 44 | I61: 53 | J61: =+AE61-SUM(G61:I61) -> 68 | K61: 53 | L61: 49 | M61: 47 | N61: =+N$56*(M61/M$56) -> 57.716612 | O61: 43 | P61: 40 | Q61: 40 | R61: =+R$56*(Q61/Q$56) -> 47.061379 | AA61: 150 | AB61: 122 | AC61: 154 | AD61: 229 | AE61: 200 | AF61: =+SUM(K61:N61) -> 206.71661 | AG61: =SUM(O61:R61) -> 170.06138 | AH61: =+AH$56*(AG61/AG$56) -> 224.21765 | AI61: =+AI$56*(AH61/AH$56) -> 235.42854 | AJ61: =+AJ$56*(AI61/AI$56) -> 259.83585 | AK61: =+AK$56*(AJ61/AJ$56) -> 261.59716 | AL61: =+AL$56*(AK61/AK$56) -> 263.44654 | AM61: =+AM$56*(AL61/AL$56) -> 263.44654 | AN61: =+AN$56*(AM61/AM$56) -> 263.44654 | AO61: =+AO$56*(AN61/AN$56) -> 263.44654 | AP61: =+AP$56*(AO61/AO$56) -> 263.44654
B62: G&A | C62: 64 | D62: 73 | E62: 73 | F62: =+AD62-SUM(C62:E62) -> 66 | G62: 74 | H62: 71 | I62: 70 | J62: =+AE62-SUM(G62:I62) -> 84 | K62: 101 | L62: 100 | M62: 113 | N62: =+N$56*(M62/M$56) -> 138.76547 | O62: 110 | P62: 95 | Q62: 86 | R62: =+R$56*(Q62/Q$56) -> 101.18197 | AA62: 313 | AB62: 269 | AC62: 259 | AD62: 276 | AE62: 299 | AF62: =+SUM(K62:N62) -> 452.76547 | AG62: =SUM(O62:R62) -> 392.18197 | AH62: =+AH$56*(AG62/AG$56) -> 517.07284 | AI62: =+AI$56*(AH62/AH$56) -> 542.92648 | AJ62: =+AJ$56*(AI62/AI$56) -> 599.21269 | AK62: =+AK$56*(AJ62/AJ$56) -> 603.27448 | AL62: =+AL$56*(AK62/AK$56) -> 607.53936 | AM62: =+AM$56*(AL62/AL$56) -> 607.53936 | AN62: =+AN$56*(AM62/AM$56) -> 607.53936 | AO62: =+AO$56*(AN62/AN$56) -> 607.53936 | AP62: =+AP$56*(AO62/AO$56) -> 607.53936
B63: Other Expense | C63: 35 | D63: 22 | E63: 11 | F63: =+AD63-SUM(C63:E63) -> 14 | G63: 8 | H63: 41 | I63: 37 | J63: =+AE63-SUM(G63:I63) -> 431 | K63: 73 | L63: 59 | M63: =55-5-18 -> 32 | N63: =+N$56*(M63/M$56) -> 39.296417 | O63: 43 | P63: =48 -> 48 | Q63: =139-87-39 -> 13 | R63: =+R$56*(Q63/Q$56) -> 15.294948 | AA63: 300 | AB63: 384 | AC63: 143 | AD63: 82 | AE63: 517 | AF63: =+SUM(K63:N63) -> 203.29642 | AG63: =SUM(O63:R63) -> 119.29495 | AH63: =+AH$56*(AG63/AG$56) -> 157.28458 | AI63: =+AI$56*(AH63/AH$56) -> 165.14881 | AJ63: =+AJ$56*(AI63/AI$56) -> 182.2701 | AK63: =+AK$56*(AJ63/AJ$56) -> 183.50563 | AL63: =+AL$56*(AK63/AK$56) -> 184.80293 | AM63: =+AM$56*(AL63/AL$56) -> 184.80293 | AN63: =+AN$56*(AM63/AM$56) -> 184.80293 | AO63: =+AO$56*(AN63/AN$56) -> 184.80293 | AP63: =+AP$56*(AO63/AO$56) -> 184.80293
B64: Other income | C64: -109 | D64: -75 | E64: 56 | F64: =+AD64-SUM(C64:E64) -> 101 | G64: 99 | H64: -17 | I64: 42 | J64: =+AE64-SUM(G64:I64) -> -212 | K64: 121 | L64: 100 | M64: 17 | N64: =+N$56*(M64/M$56) -> 20.876221 | O64: 10 | P64: =+-36 -> -36 | Q64: -55 | R64: =+R$56*(Q64/Q$56) -> -64.709397 | AA64: 297 | AB64: -32 | AC64: 125 | AD64: -27 | AE64: -88 | AF64: =+SUM(K64:N64) -> 258.87622 | AG64: =SUM(O64:R64) -> -145.7094 | AH64: =+AH$56*(AG64/AG$56) -> -192.11075 | AI64: =+AI$56*(AH64/AH$56) -> -201.71629 | AJ64: =+AJ$56*(AI64/AI$56) -> -222.62859 | AK64: =+AK$56*(AJ64/AJ$56) -> -224.13769 | AL64: =+AL$56*(AK64/AK$56) -> -225.72224 | AM64: =+AM$56*(AL64/AL$56) -> -225.72224 | AN64: =+AN$56*(AM64/AM$56) -> -225.72224 | AO64: =+AO$56*(AN64/AN$56) -> -225.72224 | AP64: =+AP$56*(AO64/AO$56) -> -225.72224
B65: Interest Expense | C65: -62 | D65: -57 | E65: -55 | F65: =+AD65-SUM(C65:E65) -> -53 | G65: -65 | H65: -49 | I65: -48 | J65: =+AE65-SUM(G65:I65) -> -81 | K65: -93 | L65: -103 | M65: -86 | N65: =+N$56*(M65/M$56) -> -105.60912 | O65: -79 | P65: -65 | Q65: -52 | R65: =+R$56*(Q65/Q$56) -> -61.179793 | AA65: -301 | AB65: -308 | AC65: -274 | AD65: -227 | AE65: -243 | AF65: =+SUM(K65:N65) -> -387.60912 | AG65: =SUM(O65:R65) -> -257.17979 | AH65: =+AH$56*(AG65/AG$56) -> -339.07904 | AI65: =+AI$56*(AH65/AH$56) -> -356.03299 | AJ65: =+AJ$56*(AI65/AI$56) -> -392.9436 | AK65: =+AK$56*(AJ65/AJ$56) -> -395.60719 | AL65: =+AL$56*(AK65/AK$56) -> -398.40396 | AM65: =+AM$56*(AL65/AL$56) -> -398.40396 | AN65: =+AN$56*(AM65/AM$56) -> -398.40396 | AO65: =+AO$56*(AN65/AN$56) -> -398.40396 | AP65: =+AP$56*(AO65/AO$56) -> -398.40396
B66: Income Before Taxes | C66: =+C56-SUM(C57:C63) + SUM(C64:C65) -> 628 | D66: =+D56-SUM(D57:D63) + SUM(D64:D65) -> 408 | E66: =+E56-SUM(E57:E63) + SUM(E64:E65) -> 296 | F66: =+F56-SUM(F57:F63) + SUM(F64:F65) -> -63 | G66: =+G56-SUM(G57:G63) + SUM(G64:G65) -> 539 | H66: =+H56-SUM(H57:H63) + SUM(H64:H65) -> 300 | I66: =+I56-SUM(I57:I63) + SUM(I64:I65) -> 232 | J66: =+J56-SUM(J57:J63) + SUM(J64:J65) -> -1211 | ... R66: =+R56-SUM(R57:R63) + SUM(R64:R65) -> 2936.6301 | AA66: =+AA56-SUM(AA57:AA65) -> 1281 | AB66: =+AB56-SUM(AB57:AB65) -> 3195 | AC66: =+AC56-SUM(AC57:AC65) -> 2002 | AD66: =+AD56-SUM(AD57:AD65) -> 1777 | AE66: =+AE56-SUM(AE57:AE65) -> 522 | AF66: =+SUM(K66:N66) -> 4861.9316 | AG66: =+AG56-SUM(AG57:AG65) -> 10410.408 | AH66: =+AH56-SUM(AH57:AH65) -> 13725.617 | AI66: =+AI56-SUM(AI57:AI65) -> 14411.898 | AJ66: =+AJ56-SUM(AJ57:AJ65) -> 15906.006 | AK66: =+AK56-SUM(AK57:AK65) -> 16013.826 | AL66: =+AL56-SUM(AL57:AL65) -> 16127.037 | AM66: =+AM56-SUM(AM57:AM65) -> 16127.037 | AN66: =+AN56-SUM(AN57:AN65) -> 16127.037 | ... AP66: =+AP56-SUM(AP57:AP65) -> 16127.037
B67: Taxes | C67: -214 | D67: -33 | E67: -96 | F67: =+AD67-SUM(C67:E67) -> -112 | G67: -213 | H67: -163 | I67: -73 | J67: =+AE67-SUM(G67:I67) -> -77 | K67: -260 | L67: -191 | M67: -244 | N67: =+N$66*(M67/M$66) -> -299.63518 | O67: -647 | P67: -1092 | Q67: -787 | R67: =+R$66*(Q67/Q$66) -> -925.93264 | AA67: -832 | AB67: -704 | AC67: -1098 | AD67: -455 | AE67: -526 | AF67: =+SUM(K67:N67) -> -994.63518 | AG67: =SUM(O67:R67) -> -3451.9326 | AH67: =+AH66*(AG67/AG66) -> -4551.2052 | AI67: =+AI66*(AH67/AH66) -> -4778.7655 | AJ67: =+AJ66*(AI67/AI66) -> -5274.1891 | AK67: =+AK66*(AJ67/AJ66) -> -5309.9404 | AL67: =+AL66*(AK67/AK66) -> -5347.4793 | AM67: =+AM66*(AL67/AL66) -> -5347.4793 | AN67: =+AN66*(AM67/AM66) -> -5347.4793 | AO67: =+AO66*(AN67/AN66) -> -5347.4793 | AP67: =+AP66*(AO67/AO66) -> -5347.4793
B68: Equity Income | C68: 39 | D68: 17 | E68: 25 | F68: =+AD68-SUM(C68:E68) -> 26 | G68: 25 | H68: 16 | I68: 3 | J68: =+AE68-SUM(G68:I68) -> 19 | K68: 7 | L68: -3 | M68: 60 | N68: =+N$66*(M68/M$66) -> 73.680782 | O68: 78 | P68: 49 | Q68: 123 | R68: =+R$66*(Q68/Q$66) -> 144.71374 | AA68: 95 | AB68: 189 | AC68: 166 | AD68: 107 | AE68: 63 | AF68: =+SUM(K68:N68) -> 137.68078 | AG68: =SUM(O68:R68) -> 394.71374 | AH68: =+AH66*(AF68/AF66) -> 388.68372 | AI68: =+AI66*(AG68/AG66) -> 546.4314 | AJ68: =+AJ66*(AH68/AH66) -> 450.42826 | AK68: =+AK66*(AI68/AI66) -> 607.16899 | AL68: =+AL66*(AJ68/AJ66) -> 456.68742 | AM68: =+AM66*(AK68/AK66) -> 611.4614 | AN68: =+AN66*(AL68/AL66) -> 456.68742 | AO68: =+AO66*(AM68/AM66) -> 611.4614 | AP68: =+AP66*(AN68/AN66) -> 456.68742
B69: Net Income | C69: =SUM(C66:C68) -> 453 | D69: =SUM(D66:D68) -> 392 | E69: =SUM(E66:E68) -> 225 | F69: =SUM(F66:F68) -> -149 | G69: =SUM(G66:G68) -> 351 | H69: =SUM(H66:H68) -> 153 | I69: =SUM(I66:I68) -> 162 | J69: =SUM(J66:J68) -> -1269 | ... R69: =SUM(R66:R68) -> 2155.4112 | AA69: =+AA66-SUM(AA67:AA68) -> 2018 | AB69: =+AB66-SUM(AB67:AB68) -> 3710 | AC69: =+AC66-SUM(AC67:AC68) -> 2934 | AD69: =+AD66-SUM(AD67:AD68) -> 2125 | AE69: =+AE66-SUM(AE67:AE68) -> 985 | AF69: =+SUM(K69:N69) -> 4004.9772 | AG69: =SUM(AG66:AG68) -> 7353.1896 | AH69: =SUM(AH66:AH68) -> 9563.0954 | AI69: =SUM(AI66:AI68) -> 10179.564 | AJ69: =SUM(AJ66:AJ68) -> 11082.246 | AK69: =SUM(AK66:AK68) -> 11311.055 | AL69: =SUM(AL66:AL68) -> 11236.245 | AM69: =SUM(AM66:AM68) -> 11391.019 | AN69: =SUM(AN66:AN68) -> 11236.245 | ... AP69: =SUM(AP66:AP68) -> 11236.245 | AQ69: =+AP69*(1+$AS$72) -> 11348.607 | AR69: =+AQ69*(1+$AS$72) -> 11462.093 | AS69: =+AR69*(1+$AS$72) -> 11576.714 | AT69: =+AS69*(1+$AS$72) -> 11692.481 | AU69: =+AT69*(1+$AS$72) -> 11809.406 | AV69: =+AU69*(1+$AS$72) -> 11927.5 | AW69: =+AV69*(1+$AS$72) -> 12046.775 | AX69: =+AW69*(1+$AS$72) -> 12167.243 | ... IG69: =+IF69*(1+$AS$72) -> 81390.66
B70: Diluted | C70: 795 | D70: 495 | E70: 795 | F70: =+F69/F71 -> -144.91251 | G70: 795 | H70: 853 | I70: 796 | J70: =+J69/J71 -> -3658.8449 | K70: 1153 | L70: 853 | M70: 1149 | N70: =+M70 -> 1149 | O70: 1127 | P70: 1112 | Q70: 1832 | R70: =+Q70 -> 1832 | AA70: 737 | AB70: 806 | AC70: 801 | AD70: 795 | AE70: 841 | AF70: =+AF69/AF71 -> 1050.5644 | AG70: =+AF70 -> 1050.5644 | AH70: =+AG70 -> 1050.5644 | AI70: =+AH70 -> 1050.5644 | AJ70: =+AI70 -> 1050.5644 | AK70: =+AJ70 -> 1050.5644 | AL70: =+AK70 -> 1050.5644 | AM70: =+AL70 -> 1050.5644 | AN70: =+AM70 -> 1050.5644 | ... AP70: =+AO70 -> 1050.5644
B71: EPS | C71: =+C69/C70 -> 0.56981132 | D71: =+D69/D70 -> 0.79191919 | E71: =+E69/E70 -> 0.28301887 | F71: =+AD71-SUM(C71:E71) -> 1.0282066 | G71: =+G69/G70 -> 0.44150943 | H71: =+H69/H70 -> 0.17936694 | I71: =+I69/I70 -> 0.20351759 | J71: =+AE71-SUM(G71:I71) -> 0.34683077 | K71: =+K69/K70 -> 0.57241977 | L71: =+L69/L70 -> 1.2754982 | M71: =+M69/M70 -> 0.88163621 | N71: =+N69/N70 -> 1.0826607 | O71: =+O69/O70 -> 1.1845608 | P71: =+P69/P70 -> 1.1016187 | Q71: =+Q69/Q70 -> 1 | R71: =+R69/R70 -> 1.1765345 | AA71: =+AA69/AA70 -> 2.7381275 | AB71: =+AB69/AB70 -> 4.6029777 | AC71: =+AC69/AC70 -> 3.6629213 | AD71: =+AD69/AD70 -> 2.672956 | AE71: =+AE69/AE70 -> 1.1712247 | AF71: =+SUM(K71:N71) -> 3.812215 | AG71: =+AG69/AG70 -> 6.9992756 | AH71: =+AH69/AH70 -> 9.1028173 | AI71: =+AI69/AI70 -> 9.6896145 | AJ71: =+AJ69/AJ70 -> 10.54885 | AK71: =+AK69/AK70 -> 10.766646 | AL71: =+AL69/AL70 -> 10.695437 | AM71: =+AM69/AM70 -> 10.842761 | AN71: =+AN69/AN70 -> 10.695437 | ... AP71: =+AP69/AP70 -> 10.695437 | AR71: Valuation
AR72: Terminal | AS72: 0.01
B73: Growth Analysis Y/Y | AR73: Discount | AS73: 0.08
B74: Gold | G74: =+IFERROR(G51/C51-1,0) -> -0.083929992 | H74: =+IFERROR(H51/D51-1,0) -> -0.12564291 | I74: =+IFERROR(I51/E51-1,0) -> 0.021276596 | J74: =+IFERROR(J51/F51-1,0) -> 0.24028269 | K74: =+IFERROR(K51/G51-1,0) -> 0.45071646 | L74: =+IFERROR(L51/H51-1,0) -> 0.52226891 | M74: =+IFERROR(M51/I51-1,0) -> 0.64375 | N74: =+IFERROR(N51/J51-1,0) -> 0.37806268 | ... R74: =+IFERROR(R51/N51-1,0) -> 0.17064296 | AB74: =+AB51/AA51-1 -> 0.14377279 | AC74: =+AC51/AB51-1 -> 0.018647343 | AD74: =+AD51/AC51-1 -> -0.012045907 | AE74: =+AE51/AD51-1 -> 0.016993088 | AF74: =+AF51/AE51-1 -> 0.48645332 | AG74: =+AG51/AF51-1 -> 0.21671536 | AH74: =+AH51/AG51-1 -> 0.31892329 | AI74: =+AI51/AH51-1 -> 0.05 | ... AP74: =+AP51/AO51-1 -> 0 | AR74: NPV | AS74: =NPV(AS73,AG69:IH69) -> 144727.04
B75: Copper | G75: =+IFERROR(G52/C52-1,0) -> 0.11111111 | H75: =+IFERROR(H52/D52-1,0) -> 0.078947368 | I75: =+IFERROR(I52/E52-1,0) -> 0.875 | J75: =+IFERROR(J52/F52-1,0) -> 2.1505376 | K75: =+IFERROR(K52/G52-1,0) -> 1.7 | L75: =+IFERROR(L52/H52-1,0) -> 3.597561 | M75: =+IFERROR(M52/I52-1,0) -> 2.6555556 | N75: =+IFERROR(N52/J52-1,0) -> 0.10580205 | ... R75: =+IFERROR(R52/N52-1,0) -> 0.0056234568 | AB75: =+AB52/AA52-1 -> -0.26190476 | AC75: =+AC52/AB52-1 -> 0.90322581 | AD75: =+AD52/AC52-1 -> 0.071186441 | AE75: =+AE52/AD52-1 -> 0.81962025 | AF75: =+AF52/AE52-1 -> 1.3078261 | AG75: =+AG52/AF52-1 -> 0.023980407 | AH75: =+AH52/AG52-1 -> 0.41048644 | AI75: =+AI52/AH52-1 -> 0.05 | ... AP75: =+AP52/AO52-1 -> 0 | AR75: Shares | AS75: =+Main!K5 -> 1091.263
B76: Silver | G76: =+IFERROR(G53/C53-1,0) -> -0.25 | H76: =+IFERROR(H53/D53-1,0) -> -0.11428571 | I76: =+IFERROR(I53/E53-1,0) -> -0.95238095 | J76: =+IFERROR(J53/F53-1,0) -> -0.39864865 | K76: =+IFERROR(K53/G53-1,0) -> 0.71794872 | L76: =+IFERROR(L53/H53-1,0) -> 0.68548387 | M76: =+IFERROR(M53/I53-1,0) -> 28.4 | N76: =+IFERROR(N53/J53-1,0) -> 1.6741573 | ... R76: =+IFERROR(R53/N53-1,0) -> 0.13694118 | AB76: =+AB53/AA53-1 -> 1.0158103 | AC76: =+AC53/AB53-1 -> 0.27647059 | AD76: =+AD53/AC53-1 -> -0.15668203 | AE76: =+AE53/AD53-1 -> -0.38979964 | AF76: =+AF53/AE53-1 -> 1.3731343 | AG76: =+AG53/AF53-1 -> 0.18565031 | AH76: =+AH53/AG53-1 -> 0.43536122 | AI76: =+AI53/AH53-1 -> 0.05 | ... AP76: =+AP53/AO53-1 -> 0 | AR76: Estimate | AS76: =+AS74/AS75 -> 132.62343
B77: Lead | G77: =+IFERROR(G54/C54-1,0) -> -0.27272727 | H77: =+IFERROR(H54/D54-1,0) -> 0.14285714 | I77: =+IFERROR(I54/E54-1,0) -> -1 | J77: =+IFERROR(J54/F54-1,0) -> -0.085714286 | K77: =+IFERROR(K54/G54-1,0) -> 0.875 | L77: =+IFERROR(L54/H54-1,0) -> 0.375 | M77: =+IFERROR(M54/I54-1,0) -> 0 | N77: =+IFERROR(N54/J54-1,0) -> 0.84375 | ... R77: =+IFERROR(R54/N54-1,0) -> -0.063898305 | AB77: =+AB54/AA54-1 -> 0.57647059 | AC77: =+AC54/AB54-1 -> 0.28358209 | AD77: =+AD54/AC54-1 -> -0.22674419 | AE77: =+AE54/AD54-1 -> -0.27819549 | AF77: =+AF54/AE54-1 -> 1.03125 | AG77: =+AG54/AF54-1 -> -0.014205128 | AH77: =+AH54/AG54-1 -> -0.042293086 | AI77: =+AI54/AH54-1 -> 0.05 | ... AP77: =+AP54/AO54-1 -> 0 | AR77: Current | AS77: =+Main!K4 -> 105
B78: Zinc | G78: =+IFERROR(G55/C55-1,0) -> -0.44285714 | H78: =+IFERROR(H55/D55-1,0) -> -0.29347826 | I78: =+IFERROR(I55/E55-1,0) -> -1.0190476 | J78: =+IFERROR(J55/F55-1,0) -> -0.64893617 | K78: =+IFERROR(K55/G55-1,0) -> 0.05982906 | L78: =+IFERROR(L55/H55-1,0) -> 1.2923077 | M78: =+IFERROR(M55/I55-1,0) -> -77 | N78: =+IFERROR(N55/J55-1,0) -> 4.969697 | ... R78: =+IFERROR(R55/N55-1,0) -> -0.060241117 | AB78: =+AB55/AA55-1 -> 1.4335664 | AC78: =+AC55/AB55-1 -> 0.61206897 | AD78: =+AD55/AC55-1 -> -0.10695187 | AE78: =+AE55/AD55-1 -> -0.5748503 | AF78: =+AF55/AE55-1 -> 1.9201878 | AG78: =+AG55/AF55-1 -> 0.12239952 | AH78: =+AH55/AG55-1 -> 0.067848868 | AI78: =+AI55/AH55-1 -> 0.05 | ... AP78: =+AP55/AO55-1 -> 0 | AR78: Upside | AS78: =+AS76/AS77-1 -> 0.26308032
B79: S Y/Y | G79: =+IFERROR(G56/C56-1,0) -> -0.11379424 | H79: =+IFERROR(H56/D56-1,0) -> -0.12262917 | I79: =+IFERROR(I56/E56-1,0) -> -0.053530752 | J79: =+IFERROR(J56/F56-1,0) -> 0.2365625 | K79: =+IFERROR(K56/G56-1,0) -> 0.50167973 | L79: =+IFERROR(L56/H56-1,0) -> 0.64070071 | M79: =+IFERROR(M56/I56-1,0) -> 0.84717208 | N79: =+IFERROR(N56/J56-1,0) -> 0.42911296 | ... R79: =+IFERROR(R56/N56-1,0) -> 0.14927966 | AB79: =+AB56/AA56-1 -> 0.18039014 | AC79: =+AC56/AB56-1 -> 0.063059929 | AD79: =+AD56/AC56-1 -> -0.025118639 | AE79: =+AE56/AD56-1 -> -0.0086445657 | AF79: =+AF56/AE56-1 -> 0.5818659 | AG79: =+AG56/AF56-1 -> 0.19615609 | AH79: =+AH56/AG56-1 -> 0.31845133 | AI79: =+AI56/AH56-1 -> 0.05 | ... AP79: =+AP56/AO56-1 -> 0
B81: Margin
B82: GM | C82: =+(C56-C57)/C56 -> 0.52530599 | D82: =+(D56-D57)/D56 -> 0.44146501 | E82: =+(E56-E57)/E56 -> 0.41343964 | F82: =+(F56-F57)/F56 -> 0.44375 | G82: =+(G56-G57)/G56 -> 0.44680851 | H82: =+(H56-H57)/H56 -> 0.4248975 | I82: =+(I56-I57)/I56 -> 0.45006017 | J82: =+(J56-J57)/J56 -> 0.41799343 | ... R82: =+(R56-R57)/R56 -> 0.6468139 | AA82: =+(AA56-AA57)/AA56 -> 0.46663244 | AB82: =+(AB56-AB57)/AB56 -> 0.56388623 | AC82: =+(AC56-AC57)/AC56 -> 0.5553101 | AD82: =+(AD56-AD57)/AD56 -> 0.45715485 | AE82: =+(AE56-AE57)/AE56 -> 0.43286488 | AF82: =+(AF56-AF57)/AF56 -> 0.49645651 | AG82: =+(AG56-AG57)/AG56 -> 0.6262482 | AH82: =+(AH56-AH57)/AH56 -> 0.6262482 | ... AP82: =+(AP56-AP57)/AP56 -> 0.6262482
B83: Gold | K83: =(K51-1690)/K51 -> 0.49416342 | L83: =(L51-1777)/L51 -> 0.5095225 | M83: =(M51-1892)/M51 -> 0.52040558 | O83: =(O51-1769)/O51 -> 0.58327444 | P83: =(P51-1677)/P51 -> 0.63400262 | Q83: =(Q51-1563)/Q51 -> 0.66523881
B84: Copper | K84: =(K52-161)/K52 -> 0.45791246 | L84: =(L52-161)/L52 -> 0.5729443 | M84: =(M52-199)/M52 -> 0.39513678 | O84: =(O52-144)/O52 -> 0.59322034 | P84: =(P52-166)/P52 -> 0.53888889 | Q84: =(Q52-141)/Q52 -> 0.55799373
B85: Silver | K85: =(K53-111)/K53 -> 0.44776119 | L85: =(L53-96)/L53 -> 0.54066986 | M85: =(M53-75)/M53 -> 0.48979592 | O85: =(O53-62)/O53 -> 0.67021277 | P85: =(P53-60)/P53 -> 0.68586387 | Q85: =(Q53-96)/Q53 -> 0.67235495
B86: Lead | K86: =(K54-36)/K54 -> 0.4 | L86: =(L54-26)/L54 -> 0.40909091 | M86: =(M54-26)/M54 -> 0.1875 | O86: =(O54-21)/O54 -> 0.5 | P86: =(P54-21)/P54 -> 0.51162791 | Q86: =(Q54-33)/Q54 -> 0.36538462
B87: Zinc | K87: =(K55-108)/K55 -> 0.12903226 | L87: =(L55-96)/L55 -> 0.3557047 | M87: =(M55-118)/M55 -> 0.22368421 | O87: =(O55-110)/O55 -> 0.39226519 | P87: =(P55-77)/P55 -> 0.45390071 | Q87: =(Q55-118)/Q55 -> 0.38219895
B89: B/S
B90: Cash | K90: 2336 | L90: 2602 | M90: 3016 | N90: 3619 | O90: 4698 | P90: 6185 | Q90: 5639
B91: Trade Recievables | K91: 782 | L91: 955 | M91: 974 | N91: 1056 | O91: 887 | P91: 637 | Q91: 1047
B92: Investments | K92: 23 | L92: 50 | M92: 43 | N92: 21 | O92: 18 | P92: 468 | Q92: 328
B93: Materials and Supplies | N93: 1081 | Q93: 1074
B94: In-Process | N94: 118 | Q94: 150
B95: Concentrate | N95: 148 | Q95: 189
B96: Precious Metals | N96: 76 | Q96: 91
B97: Inventories | K97: 1385 | L97: 1467 | M97: 1487 | N97: 1423 | O97: 1493 | P97: 1500 | Q97: 1504
B98: Stockpiles and ore on leach pads | K98: 745 | L98: 681 | M98: 688 | N98: 761 | O98: 792 | P98: 767 | Q98: 944
B99: Derivative assets | K99: 114 | L99: 71 | M99: 42 | N99: 0 | O99: 20 | P99: 0 | Q99: 0
B100: OCA | K100: 765 | L100: 874 | M100: 753 | N100: 786 | O100: 633 | P100: 740 | Q100: 744
B101: Assets held forsale | K101: 5656 | L101: 5370 | M101: 5574 | N101: 4609 | O101: 2199 | P101: 102 | Q101: 166
B102: PPE | K102: 33564 | L102: 33644 | M102: 33697 | N102: 33547 | O102: 33568 | P102: 33591 | Q102: 33621
B103: Investments | K103: 4138 | L103: 4141 | M103: 4150 | N103: 4471 | O103: 4856 | P103: 4455 | Q103: 4103
B104: Stockpiles and ore on leach pads | K104: 1837 | L104: 2002 | M104: 2114 | N104: 2266 | O104: 2409 | P104: 2540 | Q104: 2521
B105: Deferred I/T | K105: 210 | L105: 273 | M105: 229 | N105: 124 | O105: 59 | P105: 55 | Q105: 40
B106: Goodwill | K106: 2792 | L106: 2792 | M106: 2721 | N106: 2658 | O106: 2658 | P106: 2658 | Q106: 2658
B107: Derivative Assets | K107: 412 | L107: 181 | M107: 161 | N107: 142 | O107: 344 | P107: 443 | Q107: 356
...

Sheet Definitions
B3: Unit | C3: Unit of Measure
B4: $ | C4: United States Dollar
B5: % | C5: Percent
B6: A$ | C6: Australian Dollar
B7: C$ | C7: Canadian Dollar
B8: gram | C8: Metric Gram
B9: ounce | C9: Troy Ounce
B10: pound | C10: United States Pound
B11: tonne | C11: Metric Ton
B12: Abbreviation | C12: Description
B13: AISC (1) | C13: All-In Sustaining Costs
B14: ARC | C14: Asset Retirement Cost
... B59: Heap Leaching | C59: Used when ore is low grade. Process. (1) Ore is crushed.

Sheet Key Questions
B2: $M
B5: What gold price is implicitly required to justify current market cap at a mid cycle multiple?
B6: Model | D6: Notes
B7: MC | C7: =+Main!K6 -> 114582.61
B8: Net Cash | C8: =+Main!K7-Main!K8 -> 4562
B9: EV | C9: =+C7-C8 -> 110020.61
B10: Needed FCF | C10: =+C9/7 -> 15717.23 | D10: assumes ~7x fcf
B11: FY25 Gold Sold | C11: =SUM(Model!O28:R28) -> 5741
B12: Sustaining AISC | C12: =AVERAGE(1651,1593,1566) -> 1603.3333
B14: FCF Per Oz Needed | C14: =+(C10/C11) * 1000 -> 2737.7165
B15: Gold price - $1.603/oz = $2,854/oz
B16: Required Gold Price | C16: =+C12+C14 -> 4341.0498 | D16: If gold can stay above $4,000, business will naturally strengthen
B18: Average of current realized Godl Prices | C18: =AVERAGE(Model!O34:R34) -> 3335.5
B19: Current LBMA Price | C19: 4251.7 | D19: 46010
B20: Revenue Price Lag | C20: =+C19-C18 -> 916.2
B22: Incremental Rev | C22: =+(C11*C20) / 10^3 -> 5259.9042
B23: Incremental Margin | C23: 0.75
B24: After tax Conversion | C24: 0.7
B25: Incremental FCF | C25: =+C22*C23*C24 -> 2761.4497
B27: Adjusted FCF | C27: =+SUM(Model!Q140,'Key Questions'!C25) -> 8883.4497 | D27: overtime 4Q FCF should approach thise as Godl stays around $4k/oz
B28: Capex Normalization (Post Buildouts) | C28: 1500

Sheet Geology
B2: Reading Material
B3: Reserves and Resources
B4: 2024
B5: =+B4-1 -> 2023
B6: =+B5-1 -> 2022
B7: =+B6-1 -> 2021
B8: =+B7-1 -> 2020
B9: =+B8-1 -> 2019
B10: =+B9-1 -> 2018
B11: =+B10-1 -> 2017
B12: =+B11-1 -> 2016
B13: =+B12-1 -> 2015
B16: Lifecycle of a Mine
B17: Mining Process
B18: What we Mine

Sheet Operations
B9: Africa Asia Pacific
B10: Africa
B11: Ahafo North, Ghana
B12: Ahafo South, Ghana
B13: Australia
B14: Boddington, Australia
B15: Cadia, Australia
B16: Tanami, Australia
B17: Papua New Guinea
B18: Lihir, Papua New Guinea
B19: Americas
B20: Canada
... B32: Health and Safety
